[{"zip_code":"94704","forecast":[{"hour":"12","civil":"12:00 PM","sky":"74"},{"hour":"13","civil":"1:00 PM","sky":"74"},{"hour":"14","civil":"2:00 PM","sky":"74"},{"hour":"15","civil":"3:00 PM","sky":"74"},{"hour":"16","civil":"4:00 PM","sky":"74"},{"hour":"17","civil":"5:00 PM","sky":"25"},{"hour":"18","civil":"6:00 PM","sky":"25"},{"hour":"19","civil":"7:00 PM","sky":"25"},{"hour":"20","civil":"8:00 PM","sky":"25"},{"hour":"21","civil":"9:00 PM","sky":"25"},{"hour":"22","civil":"10:00 PM","sky":"25"},{"hour":"23","civil":"11:00 PM","sky":"48"},{"hour":"0","civil":"12:00 AM","sky":"48"},{"hour":"1","civil":"1:00 AM","sky":"48"},{"hour":"2","civil":"2:00 AM","sky":"48"},{"hour":"3","civil":"3:00 AM","sky":"48"},{"hour":"4","civil":"4:00 AM","sky":"48"},{"hour":"5","civil":"5:00 AM","sky":"53"},{"hour":"6","civil":"6:00 AM","sky":"53"},{"hour":"7","civil":"7:00 AM","sky":"53"},{"hour":"8","civil":"8:00 AM","sky":"53"},{"hour":"9","civil":"9:00 AM","sky":"53"},{"hour":"10","civil":"10:00 AM","sky":"53"},{"hour":"11","civil":"11:00 AM","sky":"0"},{"hour":"12","civil":"12:00 PM","sky":"0"},{"hour":"13","civil":"1:00 PM","sky":"0"},{"hour":"14","civil":"2:00 PM","sky":"0"},{"hour":"15","civil":"3:00 PM","sky":"0"},{"hour":"16","civil":"4:00 PM","sky":"0"},{"hour":"17","civil":"5:00 PM","sky":"1"},{"hour":"18","civil":"6:00 PM","sky":"1"},{"hour":"19","civil":"7:00 PM","sky":"1"},{"hour":"20","civil":"8:00 PM","sky":"1"},{"hour":"21","civil":"9:00 PM","sky":"1"},{"hour":"22","civil":"10:00 PM","sky":"1"},{"hour":"23","civil":"11:00 PM","sky":"32"}]},{"zip_code":"94124","forecast":[{"hour":"12","civil":"12:00 PM","sky":"75"},{"hour":"13","civil":"1:00 PM","sky":"75"},{"hour":"14","civil":"2:00 PM","sky":"75"},{"hour":"15","civil":"3:00 PM","sky":"75"},{"hour":"16","civil":"4:00 PM","sky":"75"},{"hour":"17","civil":"5:00 PM","sky":"32"},{"hour":"18","civil":"6:00 PM","sky":"32"},{"hour":"19","civil":"7:00 PM","sky":"32"},{"hour":"20","civil":"8:00 PM","sky":"32"},{"hour":"21","civil":"9:00 PM","sky":"32"},{"hour":"22","civil":"10:00 PM","sky":"32"},{"hour":"23","civil":"11:00 PM","sky":"76"},{"hour":"0","civil":"12:00 AM","sky":"76"},{"hour":"1","civil":"1:00 AM","sky":"76"},{"hour":"2","civil":"2:00 AM","sky":"76"},{"hour":"3","civil":"3:00 AM","sky":"76"},{"hour":"4","civil":"4:00 AM","sky":"76"},{"hour":"5","civil":"5:00 AM","sky":"79"},{"hour":"6","civil":"6:00 AM","sky":"79"},{"hour":"7","civil":"7:00 AM","sky":"79"},{"hour":"8","civil":"8:00 AM","sky":"79"},{"hour":"9","civil":"9:00 AM","sky":"79"},{"hour":"10","civil":"10:00 AM","sky":"79"},{"hour":"11","civil":"11:00 AM","sky":"0"},{"hour":"12","civil":"12:00 PM","sky":"0"},{"hour":"13","civil":"1:00 PM","sky":"0"},{"hour":"14","civil":"2:00 PM","sky":"0"},{"hour":"15","civil":"3:00 PM","sky":"0"},{"hour":"16","civil":"4:00 PM","sky":"0"},{"hour":"17","civil":"5:00 PM","sky":"26"},{"hour":"18","civil":"6:00 PM","sky":"26"},{"hour":"19","civil":"7:00 PM","sky":"26"},{"hour":"20","civil":"8:00 PM","sky":"26"},{"hour":"21","civil":"9:00 PM","sky":"26"},{"hour":"22","civil":"10:00 PM","sky":"26"},{"hour":"23","civil":"11:00 PM","sky":"91"}]},{"zip_code":"94108","forecast":[{"hour":"12","civil":"12:00 PM","sky":"71"},{"hour":"13","civil":"1:00 PM","sky":"71"},{"hour":"14","civil":"2:00 PM","sky":"71"},{"hour":"15","civil":"3:00 PM","sky":"71"},{"hour":"16","civil":"4:00 PM","sky":"71"},{"hour":"17","civil":"5:00 PM","sky":"27"},{"hour":"18","civil":"6:00 PM","sky":"27"},{"hour":"19","civil":"7:00 PM","sky":"27"},{"hour":"20","civil":"8:00 PM","sky":"27"},{"hour":"21","civil":"9:00 PM","sky":"27"},{"hour":"22","civil":"10:00 PM","sky":"27"},{"hour":"23","civil":"11:00 PM","sky":"73"},{"hour":"0","civil":"12:00 AM","sky":"73"},{"hour":"1","civil":"1:00 AM","sky":"73"},{"hour":"2","civil":"2:00 AM","sky":"73"},{"hour":"3","civil":"3:00 AM","sky":"73"},{"hour":"4","civil":"4:00 AM","sky":"73"},{"hour":"5","civil":"5:00 AM","sky":"74"},{"hour":"6","civil":"6:00 AM","sky":"74"},{"hour":"7","civil":"7:00 AM","sky":"74"},{"hour":"8","civil":"8:00 AM","sky":"74"},{"hour":"9","civil":"9:00 AM","sky":"74"},{"hour":"10","civil":"10:00 AM","sky":"74"},{"hour":"11","civil":"11:00 AM","sky":"0"},{"hour":"12","civil":"12:00 PM","sky":"0"},{"hour":"13","civil":"1:00 PM","sky":"0"},{"hour":"14","civil":"2:00 PM","sky":"0"},{"hour":"15","civil":"3:00 PM","sky":"0"},{"hour":"16","civil":"4:00 PM","sky":"0"},{"hour":"17","civil":"5:00 PM","sky":"11"},{"hour":"18","civil":"6:00 PM","sky":"11"},{"hour":"19","civil":"7:00 PM","sky":"11"},{"hour":"20","civil":"8:00 PM","sky":"11"},{"hour":"21","civil":"9:00 PM","sky":"11"},{"hour":"22","civil":"10:00 PM","sky":"11"},{"hour":"23","civil":"11:00 PM","sky":"87"}]},{"zip_code":"94603","forecast":[{"hour":"12","civil":"12:00 PM","sky":"74"},{"hour":"13","civil":"1:00 PM","sky":"74"},{"hour":"14","civil":"2:00 PM","sky":"74"},{"hour":"15","civil":"3:00 PM","sky":"74"},{"hour":"16","civil":"4:00 PM","sky":"74"},{"hour":"17","civil":"5:00 PM","sky":"28"},{"hour":"18","civil":"6:00 PM","sky":"28"},{"hour":"19","civil":"7:00 PM","sky":"28"},{"hour":"20","civil":"8:00 PM","sky":"28"},{"hour":"21","civil":"9:00 PM","sky":"28"},{"hour":"22","civil":"10:00 PM","sky":"28"},{"hour":"23","civil":"11:00 PM","sky":"92"},{"hour":"0","civil":"12:00 AM","sky":"92"},{"hour":"1","civil":"1:00 AM","sky":"92"},{"hour":"2","civil":"2:00 AM","sky":"92"},{"hour":"3","civil":"3:00 AM","sky":"92"},{"hour":"4","civil":"4:00 AM","sky":"92"},{"hour":"5","civil":"5:00 AM","sky":"80"},{"hour":"6","civil":"6:00 AM","sky":"80"},{"hour":"7","civil":"7:00 AM","sky":"80"},{"hour":"8","civil":"8:00 AM","sky":"80"},{"hour":"9","civil":"9:00 AM","sky":"80"},{"hour":"10","civil":"10:00 AM","sky":"80"},{"hour":"11","civil":"11:00 AM","sky":"0"},{"hour":"12","civil":"12:00 PM","sky":"0"},{"hour":"13","civil":"1:00 PM","sky":"0"},{"hour":"14","civil":"2:00 PM","sky":"0"},{"hour":"15","civil":"3:00 PM","sky":"0"},{"hour":"16","civil":"4:00 PM","sky":"0"},{"hour":"17","civil":"5:00 PM","sky":"4"},{"hour":"18","civil":"6:00 PM","sky":"4"},{"hour":"19","civil":"7:00 PM","sky":"4"},{"hour":"20","civil":"8:00 PM","sky":"4"},{"hour":"21","civil":"9:00 PM","sky":"4"},{"hour":"22","civil":"10:00 PM","sky":"4"},{"hour":"23","civil":"11:00 PM","sky":"90"}]},{"zip_code":"94111","forecast":[{"hour":"12","civil":"12:00 PM","sky":"71"},{"hour":"13","civil":"1:00 PM","sky":"71"},{"hour":"14","civil":"2:00 PM","sky":"71"},{"hour":"15","civil":"3:00 PM","sky":"71"},{"hour":"16","civil":"4:00 PM","sky":"71"},{"hour":"17","civil":"5:00 PM","sky":"27"},{"hour":"18","civil":"6:00 PM","sky":"27"},{"hour":"19","civil":"7:00 PM","sky":"27"},{"hour":"20","civil":"8:00 PM","sky":"27"},{"hour":"21","civil":"9:00 PM","sky":"27"},{"hour":"22","civil":"10:00 PM","sky":"27"},{"hour":"23","civil":"11:00 PM","sky":"73"},{"hour":"0","civil":"12:00 AM","sky":"73"},{"hour":"1","civil":"1:00 AM","sky":"73"},{"hour":"2","civil":"2:00 AM","sky":"73"},{"hour":"3","civil":"3:00 AM","sky":"73"},{"hour":"4","civil":"4:00 AM","sky":"73"},{"hour":"5","civil":"5:00 AM","sky":"74"},{"hour":"6","civil":"6:00 AM","sky":"74"},{"hour":"7","civil":"7:00 AM","sky":"74"},{"hour":"8","civil":"8:00 AM","sky":"74"},{"hour":"9","civil":"9:00 AM","sky":"74"},{"hour":"10","civil":"10:00 AM","sky":"74"},{"hour":"11","civil":"11:00 AM","sky":"0"},{"hour":"12","civil":"12:00 PM","sky":"0"},{"hour":"13","civil":"1:00 PM","sky":"0"},{"hour":"14","civil":"2:00 PM","sky":"0"},{"hour":"15","civil":"3:00 PM","sky":"0"},{"hour":"16","civil":"4:00 PM","sky":"0"},{"hour":"17","civil":"5:00 PM","sky":"11"},{"hour":"18","civil":"6:00 PM","sky":"11"},{"hour":"19","civil":"7:00 PM","sky":"11"},{"hour":"20","civil":"8:00 PM","sky":"11"},{"hour":"21","civil":"9:00 PM","sky":"11"},{"hour":"22","civil":"10:00 PM","sky":"11"},{"hour":"23","civil":"11:00 PM","sky":"87"}]},{"zip_code":"94607","forecast":[{"hour":"12","civil":"12:00 PM","sky":"75"},{"hour":"13","civil":"1:00 PM","sky":"75"},{"hour":"14","civil":"2:00 PM","sky":"75"},{"hour":"15","civil":"3:00 PM","sky":"75"},{"hour":"16","civil":"4:00 PM","sky":"75"},{"hour":"17","civil":"5:00 PM","sky":"26"},{"hour":"18","civil":"6:00 PM","sky":"26"},{"hour":"19","civil":"7:00 PM","sky":"26"},{"hour":"20","civil":"8:00 PM","sky":"26"},{"hour":"21","civil":"9:00 PM","sky":"26"},{"hour":"22","civil":"10:00 PM","sky":"26"},{"hour":"23","civil":"11:00 PM","sky":"73"},{"hour":"0","civil":"12:00 AM","sky":"73"},{"hour":"1","civil":"1:00 AM","sky":"73"},{"hour":"2","civil":"2:00 AM","sky":"73"},{"hour":"3","civil":"3:00 AM","sky":"73"},{"hour":"4","civil":"4:00 AM","sky":"73"},{"hour":"5","civil":"5:00 AM","sky":"73"},{"hour":"6","civil":"6:00 AM","sky":"73"},{"hour":"7","civil":"7:00 AM","sky":"73"},{"hour":"8","civil":"8:00 AM","sky":"73"},{"hour":"9","civil":"9:00 AM","sky":"73"},{"hour":"10","civil":"10:00 AM","sky":"73"},{"hour":"11","civil":"11:00 AM","sky":"0"},{"hour":"12","civil":"12:00 PM","sky":"0"},{"hour":"13","civil":"1:00 PM","sky":"0"},{"hour":"14","civil":"2:00 PM","sky":"0"},{"hour":"15","civil":"3:00 PM","sky":"0"},{"hour":"16","civil":"4:00 PM","sky":"0"},{"hour":"17","civil":"5:00 PM","sky":"2"},{"hour":"18","civil":"6:00 PM","sky":"2"},{"hour":"19","civil":"7:00 PM","sky":"2"},{"hour":"20","civil":"8:00 PM","sky":"2"},{"hour":"21","civil":"9:00 PM","sky":"2"},{"hour":"22","civil":"10:00 PM","sky":"2"},{"hour":"23","civil":"11:00 PM","sky":"79"}]},{"zip_code":"94611","forecast":[{"hour":"12","civil":"12:00 PM","sky":"75"},{"hour":"13","civil":"1:00 PM","sky":"75"},{"hour":"14","civil":"2:00 PM","sky":"75"},{"hour":"15","civil":"3:00 PM","sky":"75"},{"hour":"16","civil":"4:00 PM","sky":"75"},{"hour":"17","civil":"5:00 PM","sky":"26"},{"hour":"18","civil":"6:00 PM","sky":"26"},{"hour":"19","civil":"7:00 PM","sky":"26"},{"hour":"20","civil":"8:00 PM","sky":"26"},{"hour":"21","civil":"9:00 PM","sky":"26"},{"hour":"22","civil":"10:00 PM","sky":"26"},{"hour":"23","civil":"11:00 PM","sky":"75"},{"hour":"0","civil":"12:00 AM","sky":"75"},{"hour":"1","civil":"1:00 AM","sky":"75"},{"hour":"2","civil":"2:00 AM","sky":"75"},{"hour":"3","civil":"3:00 AM","sky":"75"},{"hour":"4","civil":"4:00 AM","sky":"75"},{"hour":"5","civil":"5:00 AM","sky":"69"},{"hour":"6","civil":"6:00 AM","sky":"69"},{"hour":"7","civil":"7:00 AM","sky":"69"},{"hour":"8","civil":"8:00 AM","sky":"69"},{"hour":"9","civil":"9:00 AM","sky":"69"},{"hour":"10","civil":"10:00 AM","sky":"69"},{"hour":"11","civil":"11:00 AM","sky":"0"},{"hour":"12","civil":"12:00 PM","sky":"0"},{"hour":"13","civil":"1:00 PM","sky":"0"},{"hour":"14","civil":"2:00 PM","sky":"0"},{"hour":"15","civil":"3:00 PM","sky":"0"},{"hour":"16","civil":"4:00 PM","sky":"0"},{"hour":"17","civil":"5:00 PM","sky":"1"},{"hour":"18","civil":"6:00 PM","sky":"1"},{"hour":"19","civil":"7:00 PM","sky":"1"},{"hour":"20","civil":"8:00 PM","sky":"1"},{"hour":"21","civil":"9:00 PM","sky":"1"},{"hour":"22","civil":"10:00 PM","sky":"1"},{"hour":"23","civil":"11:00 PM","sky":"47"}]},{"zip_code":"94621","forecast":[{"hour":"12","civil":"12:00 PM","sky":"74"},{"hour":"13","civil":"1:00 PM","sky":"74"},{"hour":"14","civil":"2:00 PM","sky":"74"},{"hour":"15","civil":"3:00 PM","sky":"74"},{"hour":"16","civil":"4:00 PM","sky":"74"},{"hour":"17","civil":"5:00 PM","sky":"28"},{"hour":"18","civil":"6:00 PM","sky":"28"},{"hour":"19","civil":"7:00 PM","sky":"28"},{"hour":"20","civil":"8:00 PM","sky":"28"},{"hour":"21","civil":"9:00 PM","sky":"28"},{"hour":"22","civil":"10:00 PM","sky":"28"},{"hour":"23","civil":"11:00 PM","sky":"92"},{"hour":"0","civil":"12:00 AM","sky":"92"},{"hour":"1","civil":"1:00 AM","sky":"92"},{"hour":"2","civil":"2:00 AM","sky":"92"},{"hour":"3","civil":"3:00 AM","sky":"92"},{"hour":"4","civil":"4:00 AM","sky":"92"},{"hour":"5","civil":"5:00 AM","sky":"80"},{"hour":"6","civil":"6:00 AM","sky":"80"},{"hour":"7","civil":"7:00 AM","sky":"80"},{"hour":"8","civil":"8:00 AM","sky":"80"},{"hour":"9","civil":"9:00 AM","sky":"80"},{"hour":"10","civil":"10:00 AM","sky":"80"},{"hour":"11","civil":"11:00 AM","sky":"0"},{"hour":"12","civil":"12:00 PM","sky":"0"},{"hour":"13","civil":"1:00 PM","sky":"0"},{"hour":"14","civil":"2:00 PM","sky":"0"},{"hour":"15","civil":"3:00 PM","sky":"0"},{"hour":"16","civil":"4:00 PM","sky":"0"},{"hour":"17","civil":"5:00 PM","sky":"4"},{"hour":"18","civil":"6:00 PM","sky":"4"},{"hour":"19","civil":"7:00 PM","sky":"4"},{"hour":"20","civil":"8:00 PM","sky":"4"},{"hour":"21","civil":"9:00 PM","sky":"4"},{"hour":"22","civil":"10:00 PM","sky":"4"},{"hour":"23","civil":"11:00 PM","sky":"90"}]},{"zip_code":"94619","forecast":[{"hour":"12","civil":"12:00 PM","sky":"74"},{"hour":"13","civil":"1:00 PM","sky":"74"},{"hour":"14","civil":"2:00 PM","sky":"74"},{"hour":"15","civil":"3:00 PM","sky":"74"},{"hour":"16","civil":"4:00 PM","sky":"74"},{"hour":"17","civil":"5:00 PM","sky":"28"},{"hour":"18","civil":"6:00 PM","sky":"28"},{"hour":"19","civil":"7:00 PM","sky":"28"},{"hour":"20","civil":"8:00 PM","sky":"28"},{"hour":"21","civil":"9:00 PM","sky":"28"},{"hour":"22","civil":"10:00 PM","sky":"28"},{"hour":"23","civil":"11:00 PM","sky":"92"},{"hour":"0","civil":"12:00 AM","sky":"92"},{"hour":"1","civil":"1:00 AM","sky":"92"},{"hour":"2","civil":"2:00 AM","sky":"92"},{"hour":"3","civil":"3:00 AM","sky":"92"},{"hour":"4","civil":"4:00 AM","sky":"92"},{"hour":"5","civil":"5:00 AM","sky":"80"},{"hour":"6","civil":"6:00 AM","sky":"80"},{"hour":"7","civil":"7:00 AM","sky":"80"},{"hour":"8","civil":"8:00 AM","sky":"80"},{"hour":"9","civil":"9:00 AM","sky":"80"},{"hour":"10","civil":"10:00 AM","sky":"80"},{"hour":"11","civil":"11:00 AM","sky":"0"},{"hour":"12","civil":"12:00 PM","sky":"0"},{"hour":"13","civil":"1:00 PM","sky":"0"},{"hour":"14","civil":"2:00 PM","sky":"0"},{"hour":"15","civil":"3:00 PM","sky":"0"},{"hour":"16","civil":"4:00 PM","sky":"0"},{"hour":"17","civil":"5:00 PM","sky":"4"},{"hour":"18","civil":"6:00 PM","sky":"4"},{"hour":"19","civil":"7:00 PM","sky":"4"},{"hour":"20","civil":"8:00 PM","sky":"4"},{"hour":"21","civil":"9:00 PM","sky":"4"},{"hour":"22","civil":"10:00 PM","sky":"4"},{"hour":"23","civil":"11:00 PM","sky":"90"}]},{"zip_code":"94130","forecast":[{"hour":"12","civil":"12:00 PM","sky":"71"},{"hour":"13","civil":"1:00 PM","sky":"71"},{"hour":"14","civil":"2:00 PM","sky":"71"},{"hour":"15","civil":"3:00 PM","sky":"71"},{"hour":"16","civil":"4:00 PM","sky":"71"},{"hour":"17","civil":"5:00 PM","sky":"27"},{"hour":"18","civil":"6:00 PM","sky":"27"},{"hour":"19","civil":"7:00 PM","sky":"27"},{"hour":"20","civil":"8:00 PM","sky":"27"},{"hour":"21","civil":"9:00 PM","sky":"27"},{"hour":"22","civil":"10:00 PM","sky":"27"},{"hour":"23","civil":"11:00 PM","sky":"73"},{"hour":"0","civil":"12:00 AM","sky":"73"},{"hour":"1","civil":"1:00 AM","sky":"73"},{"hour":"2","civil":"2:00 AM","sky":"73"},{"hour":"3","civil":"3:00 AM","sky":"73"},{"hour":"4","civil":"4:00 AM","sky":"73"},{"hour":"5","civil":"5:00 AM","sky":"74"},{"hour":"6","civil":"6:00 AM","sky":"74"},{"hour":"7","civil":"7:00 AM","sky":"74"},{"hour":"8","civil":"8:00 AM","sky":"74"},{"hour":"9","civil":"9:00 AM","sky":"74"},{"hour":"10","civil":"10:00 AM","sky":"74"},{"hour":"11","civil":"11:00 AM","sky":"0"},{"hour":"12","civil":"12:00 PM","sky":"0"},{"hour":"13","civil":"1:00 PM","sky":"0"},{"hour":"14","civil":"2:00 PM","sky":"0"},{"hour":"15","civil":"3:00 PM","sky":"0"},{"hour":"16","civil":"4:00 PM","sky":"0"},{"hour":"17","civil":"5:00 PM","sky":"11"},{"hour":"18","civil":"6:00 PM","sky":"11"},{"hour":"19","civil":"7:00 PM","sky":"11"},{"hour":"20","civil":"8:00 PM","sky":"11"},{"hour":"21","civil":"9:00 PM","sky":"11"},{"hour":"22","civil":"10:00 PM","sky":"11"},{"hour":"23","civil":"11:00 PM","sky":"87"}]},{"zip_code":"94705","forecast":[{"hour":"12","civil":"12:00 PM","sky":"74"},{"hour":"13","civil":"1:00 PM","sky":"74"},{"hour":"14","civil":"2:00 PM","sky":"74"},{"hour":"15","civil":"3:00 PM","sky":"74"},{"hour":"16","civil":"4:00 PM","sky":"74"},{"hour":"17","civil":"5:00 PM","sky":"25"},{"hour":"18","civil":"6:00 PM","sky":"25"},{"hour":"19","civil":"7:00 PM","sky":"25"},{"hour":"20","civil":"8:00 PM","sky":"25"},{"hour":"21","civil":"9:00 PM","sky":"25"},{"hour":"22","civil":"10:00 PM","sky":"25"},{"hour":"23","civil":"11:00 PM","sky":"48"},{"hour":"0","civil":"12:00 AM","sky":"48"},{"hour":"1","civil":"1:00 AM","sky":"48"},{"hour":"2","civil":"2:00 AM","sky":"48"},{"hour":"3","civil":"3:00 AM","sky":"48"},{"hour":"4","civil":"4:00 AM","sky":"48"},{"hour":"5","civil":"5:00 AM","sky":"53"},{"hour":"6","civil":"6:00 AM","sky":"53"},{"hour":"7","civil":"7:00 AM","sky":"53"},{"hour":"8","civil":"8:00 AM","sky":"53"},{"hour":"9","civil":"9:00 AM","sky":"53"},{"hour":"10","civil":"10:00 AM","sky":"53"},{"hour":"11","civil":"11:00 AM","sky":"0"},{"hour":"12","civil":"12:00 PM","sky":"0"},{"hour":"13","civil":"1:00 PM","sky":"0"},{"hour":"14","civil":"2:00 PM","sky":"0"},{"hour":"15","civil":"3:00 PM","sky":"0"},{"hour":"16","civil":"4:00 PM","sky":"0"},{"hour":"17","civil":"5:00 PM","sky":"1"},{"hour":"18","civil":"6:00 PM","sky":"1"},{"hour":"19","civil":"7:00 PM","sky":"1"},{"hour":"20","civil":"8:00 PM","sky":"1"},{"hour":"21","civil":"9:00 PM","sky":"1"},{"hour":"22","civil":"10:00 PM","sky":"1"},{"hour":"23","civil":"11:00 PM","sky":"32"}]},{"zip_code":"94602","forecast":[{"hour":"12","civil":"12:00 PM","sky":"75"},{"hour":"13","civil":"1:00 PM","sky":"75"},{"hour":"14","civil":"2:00 PM","sky":"75"},{"hour":"15","civil":"3:00 PM","sky":"75"},{"hour":"16","civil":"4:00 PM","sky":"75"},{"hour":"17","civil":"5:00 PM","sky":"26"},{"hour":"18","civil":"6:00 PM","sky":"26"},{"hour":"19","civil":"7:00 PM","sky":"26"},{"hour":"20","civil":"8:00 PM","sky":"26"},{"hour":"21","civil":"9:00 PM","sky":"26"},{"hour":"22","civil":"10:00 PM","sky":"26"},{"hour":"23","civil":"11:00 PM","sky":"75"},{"hour":"0","civil":"12:00 AM","sky":"75"},{"hour":"1","civil":"1:00 AM","sky":"75"},{"hour":"2","civil":"2:00 AM","sky":"75"},{"hour":"3","civil":"3:00 AM","sky":"75"},{"hour":"4","civil":"4:00 AM","sky":"75"},{"hour":"5","civil":"5:00 AM","sky":"69"},{"hour":"6","civil":"6:00 AM","sky":"69"},{"hour":"7","civil":"7:00 AM","sky":"69"},{"hour":"8","civil":"8:00 AM","sky":"69"},{"hour":"9","civil":"9:00 AM","sky":"69"},{"hour":"10","civil":"10:00 AM","sky":"69"},{"hour":"11","civil":"11:00 AM","sky":"0"},{"hour":"12","civil":"12:00 PM","sky":"0"},{"hour":"13","civil":"1:00 PM","sky":"0"},{"hour":"14","civil":"2:00 PM","sky":"0"},{"hour":"15","civil":"3:00 PM","sky":"0"},{"hour":"16","civil":"4:00 PM","sky":"0"},{"hour":"17","civil":"5:00 PM","sky":"1"},{"hour":"18","civil":"6:00 PM","sky":"1"},{"hour":"19","civil":"7:00 PM","sky":"1"},{"hour":"20","civil":"8:00 PM","sky":"1"},{"hour":"21","civil":"9:00 PM","sky":"1"},{"hour":"22","civil":"10:00 PM","sky":"1"},{"hour":"23","civil":"11:00 PM","sky":"47"}]},{"zip_code":"94610","forecast":[{"hour":"12","civil":"12:00 PM","sky":"75"},{"hour":"13","civil":"1:00 PM","sky":"75"},{"hour":"14","civil":"2:00 PM","sky":"75"},{"hour":"15","civil":"3:00 PM","sky":"75"},{"hour":"16","civil":"4:00 PM","sky":"75"},{"hour":"17","civil":"5:00 PM","sky":"27"},{"hour":"18","civil":"6:00 PM","sky":"27"},{"hour":"19","civil":"7:00 PM","sky":"27"},{"hour":"20","civil":"8:00 PM","sky":"27"},{"hour":"21","civil":"9:00 PM","sky":"27"},{"hour":"22","civil":"10:00 PM","sky":"27"},{"hour":"23","civil":"11:00 PM","sky":"85"},{"hour":"0","civil":"12:00 AM","sky":"85"},{"hour":"1","civil":"1:00 AM","sky":"85"},{"hour":"2","civil":"2:00 AM","sky":"85"},{"hour":"3","civil":"3:00 AM","sky":"85"},{"hour":"4","civil":"4:00 AM","sky":"85"},{"hour":"5","civil":"5:00 AM","sky":"77"},{"hour":"6","civil":"6:00 AM","sky":"77"},{"hour":"7","civil":"7:00 AM","sky":"77"},{"hour":"8","civil":"8:00 AM","sky":"77"},{"hour":"9","civil":"9:00 AM","sky":"77"},{"hour":"10","civil":"10:00 AM","sky":"77"},{"hour":"11","civil":"11:00 AM","sky":"0"},{"hour":"12","civil":"12:00 PM","sky":"0"},{"hour":"13","civil":"1:00 PM","sky":"0"},{"hour":"14","civil":"2:00 PM","sky":"0"},{"hour":"15","civil":"3:00 PM","sky":"0"},{"hour":"16","civil":"4:00 PM","sky":"0"},{"hour":"17","civil":"5:00 PM","sky":"5"},{"hour":"18","civil":"6:00 PM","sky":"5"},{"hour":"19","civil":"7:00 PM","sky":"5"},{"hour":"20","civil":"8:00 PM","sky":"5"},{"hour":"21","civil":"9:00 PM","sky":"5"},{"hour":"22","civil":"10:00 PM","sky":"5"},{"hour":"23","civil":"11:00 PM","sky":"89"}]},{"zip_code":"94707","forecast":[{"hour":"12","civil":"12:00 PM","sky":"74"},{"hour":"13","civil":"1:00 PM","sky":"74"},{"hour":"14","civil":"2:00 PM","sky":"74"},{"hour":"15","civil":"3:00 PM","sky":"74"},{"hour":"16","civil":"4:00 PM","sky":"74"},{"hour":"17","civil":"5:00 PM","sky":"26"},{"hour":"18","civil":"6:00 PM","sky":"26"},{"hour":"19","civil":"7:00 PM","sky":"26"},{"hour":"20","civil":"8:00 PM","sky":"26"},{"hour":"21","civil":"9:00 PM","sky":"26"},{"hour":"22","civil":"10:00 PM","sky":"26"},{"hour":"23","civil":"11:00 PM","sky":"71"},{"hour":"0","civil":"12:00 AM","sky":"71"},{"hour":"1","civil":"1:00 AM","sky":"71"},{"hour":"2","civil":"2:00 AM","sky":"71"},{"hour":"3","civil":"3:00 AM","sky":"71"},{"hour":"4","civil":"4:00 AM","sky":"71"},{"hour":"5","civil":"5:00 AM","sky":"71"},{"hour":"6","civil":"6:00 AM","sky":"71"},{"hour":"7","civil":"7:00 AM","sky":"71"},{"hour":"8","civil":"8:00 AM","sky":"71"},{"hour":"9","civil":"9:00 AM","sky":"71"},{"hour":"10","civil":"10:00 AM","sky":"71"},{"hour":"11","civil":"11:00 AM","sky":"0"},{"hour":"12","civil":"12:00 PM","sky":"0"},{"hour":"13","civil":"1:00 PM","sky":"0"},{"hour":"14","civil":"2:00 PM","sky":"0"},{"hour":"15","civil":"3:00 PM","sky":"0"},{"hour":"16","civil":"4:00 PM","sky":"0"},{"hour":"17","civil":"5:00 PM","sky":"2"},{"hour":"18","civil":"6:00 PM","sky":"2"},{"hour":"19","civil":"7:00 PM","sky":"2"},{"hour":"20","civil":"8:00 PM","sky":"2"},{"hour":"21","civil":"9:00 PM","sky":"2"},{"hour":"22","civil":"10:00 PM","sky":"2"},{"hour":"23","civil":"11:00 PM","sky":"68"}]},{"zip_code":"94115","forecast":[{"hour":"12","civil":"12:00 PM","sky":"69"},{"hour":"13","civil":"1:00 PM","sky":"69"},{"hour":"14","civil":"2:00 PM","sky":"69"},{"hour":"15","civil":"3:00 PM","sky":"69"},{"hour":"16","civil":"4:00 PM","sky":"69"},{"hour":"17","civil":"5:00 PM","sky":"27"},{"hour":"18","civil":"6:00 PM","sky":"27"},{"hour":"19","civil":"7:00 PM","sky":"27"},{"hour":"20","civil":"8:00 PM","sky":"27"},{"hour":"21","civil":"9:00 PM","sky":"27"},{"hour":"22","civil":"10:00 PM","sky":"27"},{"hour":"23","civil":"11:00 PM","sky":"74"},{"hour":"0","civil":"12:00 AM","sky":"74"},{"hour":"1","civil":"1:00 AM","sky":"74"},{"hour":"2","civil":"2:00 AM","sky":"74"},{"hour":"3","civil":"3:00 AM","sky":"74"},{"hour":"4","civil":"4:00 AM","sky":"74"},{"hour":"5","civil":"5:00 AM","sky":"74"},{"hour":"6","civil":"6:00 AM","sky":"74"},{"hour":"7","civil":"7:00 AM","sky":"74"},{"hour":"8","civil":"8:00 AM","sky":"74"},{"hour":"9","civil":"9:00 AM","sky":"74"},{"hour":"10","civil":"10:00 AM","sky":"74"},{"hour":"11","civil":"11:00 AM","sky":"0"},{"hour":"12","civil":"12:00 PM","sky":"0"},{"hour":"13","civil":"1:00 PM","sky":"0"},{"hour":"14","civil":"2:00 PM","sky":"0"},{"hour":"15","civil":"3:00 PM","sky":"0"},{"hour":"16","civil":"4:00 PM","sky":"0"},{"hour":"17","civil":"5:00 PM","sky":"16"},{"hour":"18","civil":"6:00 PM","sky":"16"},{"hour":"19","civil":"7:00 PM","sky":"16"},{"hour":"20","civil":"8:00 PM","sky":"16"},{"hour":"21","civil":"9:00 PM","sky":"16"},{"hour":"22","civil":"10:00 PM","sky":"16"},{"hour":"23","civil":"11:00 PM","sky":"87"}]},{"zip_code":"94105","forecast":[{"hour":"12","civil":"12:00 PM","sky":"76"},{"hour":"13","civil":"1:00 PM","sky":"76"},{"hour":"14","civil":"2:00 PM","sky":"76"},{"hour":"15","civil":"3:00 PM","sky":"76"},{"hour":"16","civil":"4:00 PM","sky":"76"},{"hour":"17","civil":"5:00 PM","sky":"31"},{"hour":"18","civil":"6:00 PM","sky":"31"},{"hour":"19","civil":"7:00 PM","sky":"31"},{"hour":"20","civil":"8:00 PM","sky":"31"},{"hour":"21","civil":"9:00 PM","sky":"31"},{"hour":"22","civil":"10:00 PM","sky":"31"},{"hour":"23","civil":"11:00 PM","sky":"75"},{"hour":"0","civil":"12:00 AM","sky":"75"},{"hour":"1","civil":"1:00 AM","sky":"75"},{"hour":"2","civil":"2:00 AM","sky":"75"},{"hour":"3","civil":"3:00 AM","sky":"75"},{"hour":"4","civil":"4:00 AM","sky":"75"},{"hour":"5","civil":"5:00 AM","sky":"77"},{"hour":"6","civil":"6:00 AM","sky":"77"},{"hour":"7","civil":"7:00 AM","sky":"77"},{"hour":"8","civil":"8:00 AM","sky":"77"},{"hour":"9","civil":"9:00 AM","sky":"77"},{"hour":"10","civil":"10:00 AM","sky":"77"},{"hour":"11","civil":"11:00 AM","sky":"0"},{"hour":"12","civil":"12:00 PM","sky":"0"},{"hour":"13","civil":"1:00 PM","sky":"0"},{"hour":"14","civil":"2:00 PM","sky":"0"},{"hour":"15","civil":"3:00 PM","sky":"0"},{"hour":"16","civil":"4:00 PM","sky":"0"},{"hour":"17","civil":"5:00 PM","sky":"18"},{"hour":"18","civil":"6:00 PM","sky":"18"},{"hour":"19","civil":"7:00 PM","sky":"18"},{"hour":"20","civil":"8:00 PM","sky":"18"},{"hour":"21","civil":"9:00 PM","sky":"18"},{"hour":"22","civil":"10:00 PM","sky":"18"},{"hour":"23","civil":"11:00 PM","sky":"91"}]},{"zip_code":"94116","forecast":[{"hour":"12","civil":"12:00 PM","sky":"73"},{"hour":"13","civil":"1:00 PM","sky":"73"},{"hour":"14","civil":"2:00 PM","sky":"73"},{"hour":"15","civil":"3:00 PM","sky":"73"},{"hour":"16","civil":"4:00 PM","sky":"73"},{"hour":"17","civil":"5:00 PM","sky":"42"},{"hour":"18","civil":"6:00 PM","sky":"42"},{"hour":"19","civil":"7:00 PM","sky":"42"},{"hour":"20","civil":"8:00 PM","sky":"42"},{"hour":"21","civil":"9:00 PM","sky":"42"},{"hour":"22","civil":"10:00 PM","sky":"42"},{"hour":"23","civil":"11:00 PM","sky":"78"},{"hour":"0","civil":"12:00 AM","sky":"78"},{"hour":"1","civil":"1:00 AM","sky":"78"},{"hour":"2","civil":"2:00 AM","sky":"78"},{"hour":"3","civil":"3:00 AM","sky":"78"},{"hour":"4","civil":"4:00 AM","sky":"78"},{"hour":"5","civil":"5:00 AM","sky":"81"},{"hour":"6","civil":"6:00 AM","sky":"81"},{"hour":"7","civil":"7:00 AM","sky":"81"},{"hour":"8","civil":"8:00 AM","sky":"81"},{"hour":"9","civil":"9:00 AM","sky":"81"},{"hour":"10","civil":"10:00 AM","sky":"81"},{"hour":"11","civil":"11:00 AM","sky":"0"},{"hour":"12","civil":"12:00 PM","sky":"0"},{"hour":"13","civil":"1:00 PM","sky":"0"},{"hour":"14","civil":"2:00 PM","sky":"0"},{"hour":"15","civil":"3:00 PM","sky":"0"},{"hour":"16","civil":"4:00 PM","sky":"0"},{"hour":"17","civil":"5:00 PM","sky":"35"},{"hour":"18","civil":"6:00 PM","sky":"35"},{"hour":"19","civil":"7:00 PM","sky":"35"},{"hour":"20","civil":"8:00 PM","sky":"35"},{"hour":"21","civil":"9:00 PM","sky":"35"},{"hour":"22","civil":"10:00 PM","sky":"35"},{"hour":"23","civil":"11:00 PM","sky":"91"}]},{"zip_code":"94102","forecast":[{"hour":"12","civil":"12:00 PM","sky":"76"},{"hour":"13","civil":"1:00 PM","sky":"76"},{"hour":"14","civil":"2:00 PM","sky":"76"},{"hour":"15","civil":"3:00 PM","sky":"76"},{"hour":"16","civil":"4:00 PM","sky":"76"},{"hour":"17","civil":"5:00 PM","sky":"30"},{"hour":"18","civil":"6:00 PM","sky":"30"},{"hour":"19","civil":"7:00 PM","sky":"30"},{"hour":"20","civil":"8:00 PM","sky":"30"},{"hour":"21","civil":"9:00 PM","sky":"30"},{"hour":"22","civil":"10:00 PM","sky":"30"},{"hour":"23","civil":"11:00 PM","sky":"75"},{"hour":"0","civil":"12:00 AM","sky":"75"},{"hour":"1","civil":"1:00 AM","sky":"75"},{"hour":"2","civil":"2:00 AM","sky":"75"},{"hour":"3","civil":"3:00 AM","sky":"75"},{"hour":"4","civil":"4:00 AM","sky":"75"},{"hour":"5","civil":"5:00 AM","sky":"77"},{"hour":"6","civil":"6:00 AM","sky":"77"},{"hour":"7","civil":"7:00 AM","sky":"77"},{"hour":"8","civil":"8:00 AM","sky":"77"},{"hour":"9","civil":"9:00 AM","sky":"77"},{"hour":"10","civil":"10:00 AM","sky":"77"},{"hour":"11","civil":"11:00 AM","sky":"0"},{"hour":"12","civil":"12:00 PM","sky":"0"},{"hour":"13","civil":"1:00 PM","sky":"0"},{"hour":"14","civil":"2:00 PM","sky":"0"},{"hour":"15","civil":"3:00 PM","sky":"0"},{"hour":"16","civil":"4:00 PM","sky":"0"},{"hour":"17","civil":"5:00 PM","sky":"23"},{"hour":"18","civil":"6:00 PM","sky":"23"},{"hour":"19","civil":"7:00 PM","sky":"23"},{"hour":"20","civil":"8:00 PM","sky":"23"},{"hour":"21","civil":"9:00 PM","sky":"23"},{"hour":"22","civil":"10:00 PM","sky":"23"},{"hour":"23","civil":"11:00 PM","sky":"91"}]},{"zip_code":"94104","forecast":[{"hour":"12","civil":"12:00 PM","sky":"71"},{"hour":"13","civil":"1:00 PM","sky":"71"},{"hour":"14","civil":"2:00 PM","sky":"71"},{"hour":"15","civil":"3:00 PM","sky":"71"},{"hour":"16","civil":"4:00 PM","sky":"71"},{"hour":"17","civil":"5:00 PM","sky":"27"},{"hour":"18","civil":"6:00 PM","sky":"27"},{"hour":"19","civil":"7:00 PM","sky":"27"},{"hour":"20","civil":"8:00 PM","sky":"27"},{"hour":"21","civil":"9:00 PM","sky":"27"},{"hour":"22","civil":"10:00 PM","sky":"27"},{"hour":"23","civil":"11:00 PM","sky":"73"},{"hour":"0","civil":"12:00 AM","sky":"73"},{"hour":"1","civil":"1:00 AM","sky":"73"},{"hour":"2","civil":"2:00 AM","sky":"73"},{"hour":"3","civil":"3:00 AM","sky":"73"},{"hour":"4","civil":"4:00 AM","sky":"73"},{"hour":"5","civil":"5:00 AM","sky":"74"},{"hour":"6","civil":"6:00 AM","sky":"74"},{"hour":"7","civil":"7:00 AM","sky":"74"},{"hour":"8","civil":"8:00 AM","sky":"74"},{"hour":"9","civil":"9:00 AM","sky":"74"},{"hour":"10","civil":"10:00 AM","sky":"74"},{"hour":"11","civil":"11:00 AM","sky":"0"},{"hour":"12","civil":"12:00 PM","sky":"0"},{"hour":"13","civil":"1:00 PM","sky":"0"},{"hour":"14","civil":"2:00 PM","sky":"0"},{"hour":"15","civil":"3:00 PM","sky":"0"},{"hour":"16","civil":"4:00 PM","sky":"0"},{"hour":"17","civil":"5:00 PM","sky":"11"},{"hour":"18","civil":"6:00 PM","sky":"11"},{"hour":"19","civil":"7:00 PM","sky":"11"},{"hour":"20","civil":"8:00 PM","sky":"11"},{"hour":"21","civil":"9:00 PM","sky":"11"},{"hour":"22","civil":"10:00 PM","sky":"11"},{"hour":"23","civil":"11:00 PM","sky":"87"}]},{"zip_code":"94107","forecast":[{"hour":"12","civil":"12:00 PM","sky":"76"},{"hour":"13","civil":"1:00 PM","sky":"76"},{"hour":"14","civil":"2:00 PM","sky":"76"},{"hour":"15","civil":"3:00 PM","sky":"76"},{"hour":"16","civil":"4:00 PM","sky":"76"},{"hour":"17","civil":"5:00 PM","sky":"31"},{"hour":"18","civil":"6:00 PM","sky":"31"},{"hour":"19","civil":"7:00 PM","sky":"31"},{"hour":"20","civil":"8:00 PM","sky":"31"},{"hour":"21","civil":"9:00 PM","sky":"31"},{"hour":"22","civil":"10:00 PM","sky":"31"},{"hour":"23","civil":"11:00 PM","sky":"75"},{"hour":"0","civil":"12:00 AM","sky":"75"},{"hour":"1","civil":"1:00 AM","sky":"75"},{"hour":"2","civil":"2:00 AM","sky":"75"},{"hour":"3","civil":"3:00 AM","sky":"75"},{"hour":"4","civil":"4:00 AM","sky":"75"},{"hour":"5","civil":"5:00 AM","sky":"77"},{"hour":"6","civil":"6:00 AM","sky":"77"},{"hour":"7","civil":"7:00 AM","sky":"77"},{"hour":"8","civil":"8:00 AM","sky":"77"},{"hour":"9","civil":"9:00 AM","sky":"77"},{"hour":"10","civil":"10:00 AM","sky":"77"},{"hour":"11","civil":"11:00 AM","sky":"0"},{"hour":"12","civil":"12:00 PM","sky":"0"},{"hour":"13","civil":"1:00 PM","sky":"0"},{"hour":"14","civil":"2:00 PM","sky":"0"},{"hour":"15","civil":"3:00 PM","sky":"0"},{"hour":"16","civil":"4:00 PM","sky":"0"},{"hour":"17","civil":"5:00 PM","sky":"18"},{"hour":"18","civil":"6:00 PM","sky":"18"},{"hour":"19","civil":"7:00 PM","sky":"18"},{"hour":"20","civil":"8:00 PM","sky":"18"},{"hour":"21","civil":"9:00 PM","sky":"18"},{"hour":"22","civil":"10:00 PM","sky":"18"},{"hour":"23","civil":"11:00 PM","sky":"91"}]},{"zip_code":"94605","forecast":[{"hour":"12","civil":"12:00 PM","sky":"74"},{"hour":"13","civil":"1:00 PM","sky":"74"},{"hour":"14","civil":"2:00 PM","sky":"74"},{"hour":"15","civil":"3:00 PM","sky":"74"},{"hour":"16","civil":"4:00 PM","sky":"74"},{"hour":"17","civil":"5:00 PM","sky":"28"},{"hour":"18","civil":"6:00 PM","sky":"28"},{"hour":"19","civil":"7:00 PM","sky":"28"},{"hour":"20","civil":"8:00 PM","sky":"28"},{"hour":"21","civil":"9:00 PM","sky":"28"},{"hour":"22","civil":"10:00 PM","sky":"28"},{"hour":"23","civil":"11:00 PM","sky":"92"},{"hour":"0","civil":"12:00 AM","sky":"92"},{"hour":"1","civil":"1:00 AM","sky":"92"},{"hour":"2","civil":"2:00 AM","sky":"92"},{"hour":"3","civil":"3:00 AM","sky":"92"},{"hour":"4","civil":"4:00 AM","sky":"92"},{"hour":"5","civil":"5:00 AM","sky":"80"},{"hour":"6","civil":"6:00 AM","sky":"80"},{"hour":"7","civil":"7:00 AM","sky":"80"},{"hour":"8","civil":"8:00 AM","sky":"80"},{"hour":"9","civil":"9:00 AM","sky":"80"},{"hour":"10","civil":"10:00 AM","sky":"80"},{"hour":"11","civil":"11:00 AM","sky":"0"},{"hour":"12","civil":"12:00 PM","sky":"0"},{"hour":"13","civil":"1:00 PM","sky":"0"},{"hour":"14","civil":"2:00 PM","sky":"0"},{"hour":"15","civil":"3:00 PM","sky":"0"},{"hour":"16","civil":"4:00 PM","sky":"0"},{"hour":"17","civil":"5:00 PM","sky":"4"},{"hour":"18","civil":"6:00 PM","sky":"4"},{"hour":"19","civil":"7:00 PM","sky":"4"},{"hour":"20","civil":"8:00 PM","sky":"4"},{"hour":"21","civil":"9:00 PM","sky":"4"},{"hour":"22","civil":"10:00 PM","sky":"4"},{"hour":"23","civil":"11:00 PM","sky":"90"}]},{"zip_code":"94123","forecast":[{"hour":"12","civil":"12:00 PM","sky":"69"},{"hour":"13","civil":"1:00 PM","sky":"69"},{"hour":"14","civil":"2:00 PM","sky":"69"},{"hour":"15","civil":"3:00 PM","sky":"69"},{"hour":"16","civil":"4:00 PM","sky":"69"},{"hour":"17","civil":"5:00 PM","sky":"27"},{"hour":"18","civil":"6:00 PM","sky":"27"},{"hour":"19","civil":"7:00 PM","sky":"27"},{"hour":"20","civil":"8:00 PM","sky":"27"},{"hour":"21","civil":"9:00 PM","sky":"27"},{"hour":"22","civil":"10:00 PM","sky":"27"},{"hour":"23","civil":"11:00 PM","sky":"74"},{"hour":"0","civil":"12:00 AM","sky":"74"},{"hour":"1","civil":"1:00 AM","sky":"74"},{"hour":"2","civil":"2:00 AM","sky":"74"},{"hour":"3","civil":"3:00 AM","sky":"74"},{"hour":"4","civil":"4:00 AM","sky":"74"},{"hour":"5","civil":"5:00 AM","sky":"74"},{"hour":"6","civil":"6:00 AM","sky":"74"},{"hour":"7","civil":"7:00 AM","sky":"74"},{"hour":"8","civil":"8:00 AM","sky":"74"},{"hour":"9","civil":"9:00 AM","sky":"74"},{"hour":"10","civil":"10:00 AM","sky":"74"},{"hour":"11","civil":"11:00 AM","sky":"0"},{"hour":"12","civil":"12:00 PM","sky":"0"},{"hour":"13","civil":"1:00 PM","sky":"0"},{"hour":"14","civil":"2:00 PM","sky":"0"},{"hour":"15","civil":"3:00 PM","sky":"0"},{"hour":"16","civil":"4:00 PM","sky":"0"},{"hour":"17","civil":"5:00 PM","sky":"16"},{"hour":"18","civil":"6:00 PM","sky":"16"},{"hour":"19","civil":"7:00 PM","sky":"16"},{"hour":"20","civil":"8:00 PM","sky":"16"},{"hour":"21","civil":"9:00 PM","sky":"16"},{"hour":"22","civil":"10:00 PM","sky":"16"},{"hour":"23","civil":"11:00 PM","sky":"87"}]},{"zip_code":"94606","forecast":[{"hour":"12","civil":"12:00 PM","sky":"75"},{"hour":"13","civil":"1:00 PM","sky":"75"},{"hour":"14","civil":"2:00 PM","sky":"75"},{"hour":"15","civil":"3:00 PM","sky":"75"},{"hour":"16","civil":"4:00 PM","sky":"75"},{"hour":"17","civil":"5:00 PM","sky":"27"},{"hour":"18","civil":"6:00 PM","sky":"27"},{"hour":"19","civil":"7:00 PM","sky":"27"},{"hour":"20","civil":"8:00 PM","sky":"27"},{"hour":"21","civil":"9:00 PM","sky":"27"},{"hour":"22","civil":"10:00 PM","sky":"27"},{"hour":"23","civil":"11:00 PM","sky":"85"},{"hour":"0","civil":"12:00 AM","sky":"85"},{"hour":"1","civil":"1:00 AM","sky":"85"},{"hour":"2","civil":"2:00 AM","sky":"85"},{"hour":"3","civil":"3:00 AM","sky":"85"},{"hour":"4","civil":"4:00 AM","sky":"85"},{"hour":"5","civil":"5:00 AM","sky":"77"},{"hour":"6","civil":"6:00 AM","sky":"77"},{"hour":"7","civil":"7:00 AM","sky":"77"},{"hour":"8","civil":"8:00 AM","sky":"77"},{"hour":"9","civil":"9:00 AM","sky":"77"},{"hour":"10","civil":"10:00 AM","sky":"77"},{"hour":"11","civil":"11:00 AM","sky":"0"},{"hour":"12","civil":"12:00 PM","sky":"0"},{"hour":"13","civil":"1:00 PM","sky":"0"},{"hour":"14","civil":"2:00 PM","sky":"0"},{"hour":"15","civil":"3:00 PM","sky":"0"},{"hour":"16","civil":"4:00 PM","sky":"0"},{"hour":"17","civil":"5:00 PM","sky":"5"},{"hour":"18","civil":"6:00 PM","sky":"5"},{"hour":"19","civil":"7:00 PM","sky":"5"},{"hour":"20","civil":"8:00 PM","sky":"5"},{"hour":"21","civil":"9:00 PM","sky":"5"},{"hour":"22","civil":"10:00 PM","sky":"5"},{"hour":"23","civil":"11:00 PM","sky":"89"}]},{"zip_code":"94158","forecast":[{"hour":"12","civil":"12:00 PM","sky":"76"},{"hour":"13","civil":"1:00 PM","sky":"76"},{"hour":"14","civil":"2:00 PM","sky":"76"},{"hour":"15","civil":"3:00 PM","sky":"76"},{"hour":"16","civil":"4:00 PM","sky":"76"},{"hour":"17","civil":"5:00 PM","sky":"31"},{"hour":"18","civil":"6:00 PM","sky":"31"},{"hour":"19","civil":"7:00 PM","sky":"31"},{"hour":"20","civil":"8:00 PM","sky":"31"},{"hour":"21","civil":"9:00 PM","sky":"31"},{"hour":"22","civil":"10:00 PM","sky":"31"},{"hour":"23","civil":"11:00 PM","sky":"75"},{"hour":"0","civil":"12:00 AM","sky":"75"},{"hour":"1","civil":"1:00 AM","sky":"75"},{"hour":"2","civil":"2:00 AM","sky":"75"},{"hour":"3","civil":"3:00 AM","sky":"75"},{"hour":"4","civil":"4:00 AM","sky":"75"},{"hour":"5","civil":"5:00 AM","sky":"77"},{"hour":"6","civil":"6:00 AM","sky":"77"},{"hour":"7","civil":"7:00 AM","sky":"77"},{"hour":"8","civil":"8:00 AM","sky":"77"},{"hour":"9","civil":"9:00 AM","sky":"77"},{"hour":"10","civil":"10:00 AM","sky":"77"},{"hour":"11","civil":"11:00 AM","sky":"0"},{"hour":"12","civil":"12:00 PM","sky":"0"},{"hour":"13","civil":"1:00 PM","sky":"0"},{"hour":"14","civil":"2:00 PM","sky":"0"},{"hour":"15","civil":"3:00 PM","sky":"0"},{"hour":"16","civil":"4:00 PM","sky":"0"},{"hour":"17","civil":"5:00 PM","sky":"18"},{"hour":"18","civil":"6:00 PM","sky":"18"},{"hour":"19","civil":"7:00 PM","sky":"18"},{"hour":"20","civil":"8:00 PM","sky":"18"},{"hour":"21","civil":"9:00 PM","sky":"18"},{"hour":"22","civil":"10:00 PM","sky":"18"},{"hour":"23","civil":"11:00 PM","sky":"91"}]},{"zip_code":"94618","forecast":[{"hour":"12","civil":"12:00 PM","sky":"74"},{"hour":"13","civil":"1:00 PM","sky":"74"},{"hour":"14","civil":"2:00 PM","sky":"74"},{"hour":"15","civil":"3:00 PM","sky":"74"},{"hour":"16","civil":"4:00 PM","sky":"74"},{"hour":"17","civil":"5:00 PM","sky":"25"},{"hour":"18","civil":"6:00 PM","sky":"25"},{"hour":"19","civil":"7:00 PM","sky":"25"},{"hour":"20","civil":"8:00 PM","sky":"25"},{"hour":"21","civil":"9:00 PM","sky":"25"},{"hour":"22","civil":"10:00 PM","sky":"25"},{"hour":"23","civil":"11:00 PM","sky":"48"},{"hour":"0","civil":"12:00 AM","sky":"48"},{"hour":"1","civil":"1:00 AM","sky":"48"},{"hour":"2","civil":"2:00 AM","sky":"48"},{"hour":"3","civil":"3:00 AM","sky":"48"},{"hour":"4","civil":"4:00 AM","sky":"48"},{"hour":"5","civil":"5:00 AM","sky":"53"},{"hour":"6","civil":"6:00 AM","sky":"53"},{"hour":"7","civil":"7:00 AM","sky":"53"},{"hour":"8","civil":"8:00 AM","sky":"53"},{"hour":"9","civil":"9:00 AM","sky":"53"},{"hour":"10","civil":"10:00 AM","sky":"53"},{"hour":"11","civil":"11:00 AM","sky":"0"},{"hour":"12","civil":"12:00 PM","sky":"0"},{"hour":"13","civil":"1:00 PM","sky":"0"},{"hour":"14","civil":"2:00 PM","sky":"0"},{"hour":"15","civil":"3:00 PM","sky":"0"},{"hour":"16","civil":"4:00 PM","sky":"0"},{"hour":"17","civil":"5:00 PM","sky":"1"},{"hour":"18","civil":"6:00 PM","sky":"1"},{"hour":"19","civil":"7:00 PM","sky":"1"},{"hour":"20","civil":"8:00 PM","sky":"1"},{"hour":"21","civil":"9:00 PM","sky":"1"},{"hour":"22","civil":"10:00 PM","sky":"1"},{"hour":"23","civil":"11:00 PM","sky":"32"}]},{"zip_code":"94121","forecast":[{"hour":"12","civil":"12:00 PM","sky":"66"},{"hour":"13","civil":"1:00 PM","sky":"66"},{"hour":"14","civil":"2:00 PM","sky":"66"},{"hour":"15","civil":"3:00 PM","sky":"66"},{"hour":"16","civil":"4:00 PM","sky":"66"},{"hour":"17","civil":"5:00 PM","sky":"32"},{"hour":"18","civil":"6:00 PM","sky":"32"},{"hour":"19","civil":"7:00 PM","sky":"32"},{"hour":"20","civil":"8:00 PM","sky":"32"},{"hour":"21","civil":"9:00 PM","sky":"32"},{"hour":"22","civil":"10:00 PM","sky":"32"},{"hour":"23","civil":"11:00 PM","sky":"75"},{"hour":"0","civil":"12:00 AM","sky":"75"},{"hour":"1","civil":"1:00 AM","sky":"75"},{"hour":"2","civil":"2:00 AM","sky":"75"},{"hour":"3","civil":"3:00 AM","sky":"75"},{"hour":"4","civil":"4:00 AM","sky":"75"},{"hour":"5","civil":"5:00 AM","sky":"76"},{"hour":"6","civil":"6:00 AM","sky":"76"},{"hour":"7","civil":"7:00 AM","sky":"76"},{"hour":"8","civil":"8:00 AM","sky":"76"},{"hour":"9","civil":"9:00 AM","sky":"76"},{"hour":"10","civil":"10:00 AM","sky":"76"},{"hour":"11","civil":"11:00 AM","sky":"0"},{"hour":"12","civil":"12:00 PM","sky":"0"},{"hour":"13","civil":"1:00 PM","sky":"0"},{"hour":"14","civil":"2:00 PM","sky":"0"},{"hour":"15","civil":"3:00 PM","sky":"0"},{"hour":"16","civil":"4:00 PM","sky":"0"},{"hour":"17","civil":"5:00 PM","sky":"23"},{"hour":"18","civil":"6:00 PM","sky":"23"},{"hour":"19","civil":"7:00 PM","sky":"23"},{"hour":"20","civil":"8:00 PM","sky":"23"},{"hour":"21","civil":"9:00 PM","sky":"23"},{"hour":"22","civil":"10:00 PM","sky":"23"},{"hour":"23","civil":"11:00 PM","sky":"87"}]},{"zip_code":"94708","forecast":[{"hour":"12","civil":"12:00 PM","sky":"74"},{"hour":"13","civil":"1:00 PM","sky":"74"},{"hour":"14","civil":"2:00 PM","sky":"74"},{"hour":"15","civil":"3:00 PM","sky":"74"},{"hour":"16","civil":"4:00 PM","sky":"74"},{"hour":"17","civil":"5:00 PM","sky":"26"},{"hour":"18","civil":"6:00 PM","sky":"26"},{"hour":"19","civil":"7:00 PM","sky":"26"},{"hour":"20","civil":"8:00 PM","sky":"26"},{"hour":"21","civil":"9:00 PM","sky":"26"},{"hour":"22","civil":"10:00 PM","sky":"26"},{"hour":"23","civil":"11:00 PM","sky":"68"},{"hour":"0","civil":"12:00 AM","sky":"68"},{"hour":"1","civil":"1:00 AM","sky":"68"},{"hour":"2","civil":"2:00 AM","sky":"68"},{"hour":"3","civil":"3:00 AM","sky":"68"},{"hour":"4","civil":"4:00 AM","sky":"68"},{"hour":"5","civil":"5:00 AM","sky":"65"},{"hour":"6","civil":"6:00 AM","sky":"65"},{"hour":"7","civil":"7:00 AM","sky":"65"},{"hour":"8","civil":"8:00 AM","sky":"65"},{"hour":"9","civil":"9:00 AM","sky":"65"},{"hour":"10","civil":"10:00 AM","sky":"65"},{"hour":"11","civil":"11:00 AM","sky":"0"},{"hour":"12","civil":"12:00 PM","sky":"0"},{"hour":"13","civil":"1:00 PM","sky":"0"},{"hour":"14","civil":"2:00 PM","sky":"0"},{"hour":"15","civil":"3:00 PM","sky":"0"},{"hour":"16","civil":"4:00 PM","sky":"0"},{"hour":"17","civil":"5:00 PM","sky":"2"},{"hour":"18","civil":"6:00 PM","sky":"2"},{"hour":"19","civil":"7:00 PM","sky":"2"},{"hour":"20","civil":"8:00 PM","sky":"2"},{"hour":"21","civil":"9:00 PM","sky":"2"},{"hour":"22","civil":"10:00 PM","sky":"2"},{"hour":"23","civil":"11:00 PM","sky":"42"}]},{"zip_code":"94601","forecast":[{"hour":"12","civil":"12:00 PM","sky":"70"},{"hour":"13","civil":"1:00 PM","sky":"70"},{"hour":"14","civil":"2:00 PM","sky":"70"},{"hour":"15","civil":"3:00 PM","sky":"70"},{"hour":"16","civil":"4:00 PM","sky":"70"},{"hour":"17","civil":"5:00 PM","sky":"28"},{"hour":"18","civil":"6:00 PM","sky":"28"},{"hour":"19","civil":"7:00 PM","sky":"28"},{"hour":"20","civil":"8:00 PM","sky":"28"},{"hour":"21","civil":"9:00 PM","sky":"28"},{"hour":"22","civil":"10:00 PM","sky":"28"},{"hour":"23","civil":"11:00 PM","sky":"86"},{"hour":"0","civil":"12:00 AM","sky":"86"},{"hour":"1","civil":"1:00 AM","sky":"86"},{"hour":"2","civil":"2:00 AM","sky":"86"},{"hour":"3","civil":"3:00 AM","sky":"86"},{"hour":"4","civil":"4:00 AM","sky":"86"},{"hour":"5","civil":"5:00 AM","sky":"80"},{"hour":"6","civil":"6:00 AM","sky":"80"},{"hour":"7","civil":"7:00 AM","sky":"80"},{"hour":"8","civil":"8:00 AM","sky":"80"},{"hour":"9","civil":"9:00 AM","sky":"80"},{"hour":"10","civil":"10:00 AM","sky":"80"},{"hour":"11","civil":"11:00 AM","sky":"0"},{"hour":"12","civil":"12:00 PM","sky":"0"},{"hour":"13","civil":"1:00 PM","sky":"0"},{"hour":"14","civil":"2:00 PM","sky":"0"},{"hour":"15","civil":"3:00 PM","sky":"0"},{"hour":"16","civil":"4:00 PM","sky":"0"},{"hour":"17","civil":"5:00 PM","sky":"9"},{"hour":"18","civil":"6:00 PM","sky":"9"},{"hour":"19","civil":"7:00 PM","sky":"9"},{"hour":"20","civil":"8:00 PM","sky":"9"},{"hour":"21","civil":"9:00 PM","sky":"9"},{"hour":"22","civil":"10:00 PM","sky":"9"},{"hour":"23","civil":"11:00 PM","sky":"90"}]},{"zip_code":"94703","forecast":[{"hour":"12","civil":"12:00 PM","sky":"75"},{"hour":"13","civil":"1:00 PM","sky":"75"},{"hour":"14","civil":"2:00 PM","sky":"75"},{"hour":"15","civil":"3:00 PM","sky":"75"},{"hour":"16","civil":"4:00 PM","sky":"75"},{"hour":"17","civil":"5:00 PM","sky":"27"},{"hour":"18","civil":"6:00 PM","sky":"27"},{"hour":"19","civil":"7:00 PM","sky":"27"},{"hour":"20","civil":"8:00 PM","sky":"27"},{"hour":"21","civil":"9:00 PM","sky":"27"},{"hour":"22","civil":"10:00 PM","sky":"27"},{"hour":"23","civil":"11:00 PM","sky":"80"},{"hour":"0","civil":"12:00 AM","sky":"80"},{"hour":"1","civil":"1:00 AM","sky":"80"},{"hour":"2","civil":"2:00 AM","sky":"80"},{"hour":"3","civil":"3:00 AM","sky":"80"},{"hour":"4","civil":"4:00 AM","sky":"80"},{"hour":"5","civil":"5:00 AM","sky":"76"},{"hour":"6","civil":"6:00 AM","sky":"76"},{"hour":"7","civil":"7:00 AM","sky":"76"},{"hour":"8","civil":"8:00 AM","sky":"76"},{"hour":"9","civil":"9:00 AM","sky":"76"},{"hour":"10","civil":"10:00 AM","sky":"76"},{"hour":"11","civil":"11:00 AM","sky":"0"},{"hour":"12","civil":"12:00 PM","sky":"0"},{"hour":"13","civil":"1:00 PM","sky":"0"},{"hour":"14","civil":"2:00 PM","sky":"0"},{"hour":"15","civil":"3:00 PM","sky":"0"},{"hour":"16","civil":"4:00 PM","sky":"0"},{"hour":"17","civil":"5:00 PM","sky":"2"},{"hour":"18","civil":"6:00 PM","sky":"2"},{"hour":"19","civil":"7:00 PM","sky":"2"},{"hour":"20","civil":"8:00 PM","sky":"2"},{"hour":"21","civil":"9:00 PM","sky":"2"},{"hour":"22","civil":"10:00 PM","sky":"2"},{"hour":"23","civil":"11:00 PM","sky":"89"}]},{"zip_code":"94131","forecast":[{"hour":"12","civil":"12:00 PM","sky":"75"},{"hour":"13","civil":"1:00 PM","sky":"75"},{"hour":"14","civil":"2:00 PM","sky":"75"},{"hour":"15","civil":"3:00 PM","sky":"75"},{"hour":"16","civil":"4:00 PM","sky":"75"},{"hour":"17","civil":"5:00 PM","sky":"30"},{"hour":"18","civil":"6:00 PM","sky":"30"},{"hour":"19","civil":"7:00 PM","sky":"30"},{"hour":"20","civil":"8:00 PM","sky":"30"},{"hour":"21","civil":"9:00 PM","sky":"30"},{"hour":"22","civil":"10:00 PM","sky":"30"},{"hour":"23","civil":"11:00 PM","sky":"75"},{"hour":"0","civil":"12:00 AM","sky":"75"},{"hour":"1","civil":"1:00 AM","sky":"75"},{"hour":"2","civil":"2:00 AM","sky":"75"},{"hour":"3","civil":"3:00 AM","sky":"75"},{"hour":"4","civil":"4:00 AM","sky":"75"},{"hour":"5","civil":"5:00 AM","sky":"77"},{"hour":"6","civil":"6:00 AM","sky":"77"},{"hour":"7","civil":"7:00 AM","sky":"77"},{"hour":"8","civil":"8:00 AM","sky":"77"},{"hour":"9","civil":"9:00 AM","sky":"77"},{"hour":"10","civil":"10:00 AM","sky":"77"},{"hour":"11","civil":"11:00 AM","sky":"0"},{"hour":"12","civil":"12:00 PM","sky":"0"},{"hour":"13","civil":"1:00 PM","sky":"0"},{"hour":"14","civil":"2:00 PM","sky":"0"},{"hour":"15","civil":"3:00 PM","sky":"0"},{"hour":"16","civil":"4:00 PM","sky":"0"},{"hour":"17","civil":"5:00 PM","sky":"28"},{"hour":"18","civil":"6:00 PM","sky":"28"},{"hour":"19","civil":"7:00 PM","sky":"28"},{"hour":"20","civil":"8:00 PM","sky":"28"},{"hour":"21","civil":"9:00 PM","sky":"28"},{"hour":"22","civil":"10:00 PM","sky":"28"},{"hour":"23","civil":"11:00 PM","sky":"91"}]},{"zip_code":"94134","forecast":[{"hour":"12","civil":"12:00 PM","sky":"75"},{"hour":"13","civil":"1:00 PM","sky":"75"},{"hour":"14","civil":"2:00 PM","sky":"75"},{"hour":"15","civil":"3:00 PM","sky":"75"},{"hour":"16","civil":"4:00 PM","sky":"75"},{"hour":"17","civil":"5:00 PM","sky":"32"},{"hour":"18","civil":"6:00 PM","sky":"32"},{"hour":"19","civil":"7:00 PM","sky":"32"},{"hour":"20","civil":"8:00 PM","sky":"32"},{"hour":"21","civil":"9:00 PM","sky":"32"},{"hour":"22","civil":"10:00 PM","sky":"32"},{"hour":"23","civil":"11:00 PM","sky":"76"},{"hour":"0","civil":"12:00 AM","sky":"76"},{"hour":"1","civil":"1:00 AM","sky":"76"},{"hour":"2","civil":"2:00 AM","sky":"76"},{"hour":"3","civil":"3:00 AM","sky":"76"},{"hour":"4","civil":"4:00 AM","sky":"76"},{"hour":"5","civil":"5:00 AM","sky":"79"},{"hour":"6","civil":"6:00 AM","sky":"79"},{"hour":"7","civil":"7:00 AM","sky":"79"},{"hour":"8","civil":"8:00 AM","sky":"79"},{"hour":"9","civil":"9:00 AM","sky":"79"},{"hour":"10","civil":"10:00 AM","sky":"79"},{"hour":"11","civil":"11:00 AM","sky":"0"},{"hour":"12","civil":"12:00 PM","sky":"0"},{"hour":"13","civil":"1:00 PM","sky":"0"},{"hour":"14","civil":"2:00 PM","sky":"0"},{"hour":"15","civil":"3:00 PM","sky":"0"},{"hour":"16","civil":"4:00 PM","sky":"0"},{"hour":"17","civil":"5:00 PM","sky":"26"},{"hour":"18","civil":"6:00 PM","sky":"26"},{"hour":"19","civil":"7:00 PM","sky":"26"},{"hour":"20","civil":"8:00 PM","sky":"26"},{"hour":"21","civil":"9:00 PM","sky":"26"},{"hour":"22","civil":"10:00 PM","sky":"26"},{"hour":"23","civil":"11:00 PM","sky":"91"}]},{"zip_code":"94114","forecast":[{"hour":"12","civil":"12:00 PM","sky":"75"},{"hour":"13","civil":"1:00 PM","sky":"75"},{"hour":"14","civil":"2:00 PM","sky":"75"},{"hour":"15","civil":"3:00 PM","sky":"75"},{"hour":"16","civil":"4:00 PM","sky":"75"},{"hour":"17","civil":"5:00 PM","sky":"31"},{"hour":"18","civil":"6:00 PM","sky":"31"},{"hour":"19","civil":"7:00 PM","sky":"31"},{"hour":"20","civil":"8:00 PM","sky":"31"},{"hour":"21","civil":"9:00 PM","sky":"31"},{"hour":"22","civil":"10:00 PM","sky":"31"},{"hour":"23","civil":"11:00 PM","sky":"76"},{"hour":"0","civil":"12:00 AM","sky":"76"},{"hour":"1","civil":"1:00 AM","sky":"76"},{"hour":"2","civil":"2:00 AM","sky":"76"},{"hour":"3","civil":"3:00 AM","sky":"76"},{"hour":"4","civil":"4:00 AM","sky":"76"},{"hour":"5","civil":"5:00 AM","sky":"78"},{"hour":"6","civil":"6:00 AM","sky":"78"},{"hour":"7","civil":"7:00 AM","sky":"78"},{"hour":"8","civil":"8:00 AM","sky":"78"},{"hour":"9","civil":"9:00 AM","sky":"78"},{"hour":"10","civil":"10:00 AM","sky":"78"},{"hour":"11","civil":"11:00 AM","sky":"0"},{"hour":"12","civil":"12:00 PM","sky":"0"},{"hour":"13","civil":"1:00 PM","sky":"0"},{"hour":"14","civil":"2:00 PM","sky":"0"},{"hour":"15","civil":"3:00 PM","sky":"0"},{"hour":"16","civil":"4:00 PM","sky":"0"},{"hour":"17","civil":"5:00 PM","sky":"29"},{"hour":"18","civil":"6:00 PM","sky":"29"},{"hour":"19","civil":"7:00 PM","sky":"29"},{"hour":"20","civil":"8:00 PM","sky":"29"},{"hour":"21","civil":"9:00 PM","sky":"29"},{"hour":"22","civil":"10:00 PM","sky":"29"},{"hour":"23","civil":"11:00 PM","sky":"91"}]},{"zip_code":"94110","forecast":[{"hour":"12","civil":"12:00 PM","sky":"75"},{"hour":"13","civil":"1:00 PM","sky":"75"},{"hour":"14","civil":"2:00 PM","sky":"75"},{"hour":"15","civil":"3:00 PM","sky":"75"},{"hour":"16","civil":"4:00 PM","sky":"75"},{"hour":"17","civil":"5:00 PM","sky":"29"},{"hour":"18","civil":"6:00 PM","sky":"29"},{"hour":"19","civil":"7:00 PM","sky":"29"},{"hour":"20","civil":"8:00 PM","sky":"29"},{"hour":"21","civil":"9:00 PM","sky":"29"},{"hour":"22","civil":"10:00 PM","sky":"29"},{"hour":"23","civil":"11:00 PM","sky":"75"},{"hour":"0","civil":"12:00 AM","sky":"75"},{"hour":"1","civil":"1:00 AM","sky":"75"},{"hour":"2","civil":"2:00 AM","sky":"75"},{"hour":"3","civil":"3:00 AM","sky":"75"},{"hour":"4","civil":"4:00 AM","sky":"75"},{"hour":"5","civil":"5:00 AM","sky":"76"},{"hour":"6","civil":"6:00 AM","sky":"76"},{"hour":"7","civil":"7:00 AM","sky":"76"},{"hour":"8","civil":"8:00 AM","sky":"76"},{"hour":"9","civil":"9:00 AM","sky":"76"},{"hour":"10","civil":"10:00 AM","sky":"76"},{"hour":"11","civil":"11:00 AM","sky":"0"},{"hour":"12","civil":"12:00 PM","sky":"0"},{"hour":"13","civil":"1:00 PM","sky":"0"},{"hour":"14","civil":"2:00 PM","sky":"0"},{"hour":"15","civil":"3:00 PM","sky":"0"},{"hour":"16","civil":"4:00 PM","sky":"0"},{"hour":"17","civil":"5:00 PM","sky":"27"},{"hour":"18","civil":"6:00 PM","sky":"27"},{"hour":"19","civil":"7:00 PM","sky":"27"},{"hour":"20","civil":"8:00 PM","sky":"27"},{"hour":"21","civil":"9:00 PM","sky":"27"},{"hour":"22","civil":"10:00 PM","sky":"27"},{"hour":"23","civil":"11:00 PM","sky":"91"}]},{"zip_code":"94133","forecast":[{"hour":"12","civil":"12:00 PM","sky":"71"},{"hour":"13","civil":"1:00 PM","sky":"71"},{"hour":"14","civil":"2:00 PM","sky":"71"},{"hour":"15","civil":"3:00 PM","sky":"71"},{"hour":"16","civil":"4:00 PM","sky":"71"},{"hour":"17","civil":"5:00 PM","sky":"27"},{"hour":"18","civil":"6:00 PM","sky":"27"},{"hour":"19","civil":"7:00 PM","sky":"27"},{"hour":"20","civil":"8:00 PM","sky":"27"},{"hour":"21","civil":"9:00 PM","sky":"27"},{"hour":"22","civil":"10:00 PM","sky":"27"},{"hour":"23","civil":"11:00 PM","sky":"73"},{"hour":"0","civil":"12:00 AM","sky":"73"},{"hour":"1","civil":"1:00 AM","sky":"73"},{"hour":"2","civil":"2:00 AM","sky":"73"},{"hour":"3","civil":"3:00 AM","sky":"73"},{"hour":"4","civil":"4:00 AM","sky":"73"},{"hour":"5","civil":"5:00 AM","sky":"74"},{"hour":"6","civil":"6:00 AM","sky":"74"},{"hour":"7","civil":"7:00 AM","sky":"74"},{"hour":"8","civil":"8:00 AM","sky":"74"},{"hour":"9","civil":"9:00 AM","sky":"74"},{"hour":"10","civil":"10:00 AM","sky":"74"},{"hour":"11","civil":"11:00 AM","sky":"0"},{"hour":"12","civil":"12:00 PM","sky":"0"},{"hour":"13","civil":"1:00 PM","sky":"0"},{"hour":"14","civil":"2:00 PM","sky":"0"},{"hour":"15","civil":"3:00 PM","sky":"0"},{"hour":"16","civil":"4:00 PM","sky":"0"},{"hour":"17","civil":"5:00 PM","sky":"11"},{"hour":"18","civil":"6:00 PM","sky":"11"},{"hour":"19","civil":"7:00 PM","sky":"11"},{"hour":"20","civil":"8:00 PM","sky":"11"},{"hour":"21","civil":"9:00 PM","sky":"11"},{"hour":"22","civil":"10:00 PM","sky":"11"},{"hour":"23","civil":"11:00 PM","sky":"87"}]},{"zip_code":"94709","forecast":[{"hour":"12","civil":"12:00 PM","sky":"74"},{"hour":"13","civil":"1:00 PM","sky":"74"},{"hour":"14","civil":"2:00 PM","sky":"74"},{"hour":"15","civil":"3:00 PM","sky":"74"},{"hour":"16","civil":"4:00 PM","sky":"74"},{"hour":"17","civil":"5:00 PM","sky":"26"},{"hour":"18","civil":"6:00 PM","sky":"26"},{"hour":"19","civil":"7:00 PM","sky":"26"},{"hour":"20","civil":"8:00 PM","sky":"26"},{"hour":"21","civil":"9:00 PM","sky":"26"},{"hour":"22","civil":"10:00 PM","sky":"26"},{"hour":"23","civil":"11:00 PM","sky":"68"},{"hour":"0","civil":"12:00 AM","sky":"68"},{"hour":"1","civil":"1:00 AM","sky":"68"},{"hour":"2","civil":"2:00 AM","sky":"68"},{"hour":"3","civil":"3:00 AM","sky":"68"},{"hour":"4","civil":"4:00 AM","sky":"68"},{"hour":"5","civil":"5:00 AM","sky":"65"},{"hour":"6","civil":"6:00 AM","sky":"65"},{"hour":"7","civil":"7:00 AM","sky":"65"},{"hour":"8","civil":"8:00 AM","sky":"65"},{"hour":"9","civil":"9:00 AM","sky":"65"},{"hour":"10","civil":"10:00 AM","sky":"65"},{"hour":"11","civil":"11:00 AM","sky":"0"},{"hour":"12","civil":"12:00 PM","sky":"0"},{"hour":"13","civil":"1:00 PM","sky":"0"},{"hour":"14","civil":"2:00 PM","sky":"0"},{"hour":"15","civil":"3:00 PM","sky":"0"},{"hour":"16","civil":"4:00 PM","sky":"0"},{"hour":"17","civil":"5:00 PM","sky":"2"},{"hour":"18","civil":"6:00 PM","sky":"2"},{"hour":"19","civil":"7:00 PM","sky":"2"},{"hour":"20","civil":"8:00 PM","sky":"2"},{"hour":"21","civil":"9:00 PM","sky":"2"},{"hour":"22","civil":"10:00 PM","sky":"2"},{"hour":"23","civil":"11:00 PM","sky":"42"}]},{"zip_code":"94612","forecast":[{"hour":"12","civil":"12:00 PM","sky":"75"},{"hour":"13","civil":"1:00 PM","sky":"75"},{"hour":"14","civil":"2:00 PM","sky":"75"},{"hour":"15","civil":"3:00 PM","sky":"75"},{"hour":"16","civil":"4:00 PM","sky":"75"},{"hour":"17","civil":"5:00 PM","sky":"26"},{"hour":"18","civil":"6:00 PM","sky":"26"},{"hour":"19","civil":"7:00 PM","sky":"26"},{"hour":"20","civil":"8:00 PM","sky":"26"},{"hour":"21","civil":"9:00 PM","sky":"26"},{"hour":"22","civil":"10:00 PM","sky":"26"},{"hour":"23","civil":"11:00 PM","sky":"73"},{"hour":"0","civil":"12:00 AM","sky":"73"},{"hour":"1","civil":"1:00 AM","sky":"73"},{"hour":"2","civil":"2:00 AM","sky":"73"},{"hour":"3","civil":"3:00 AM","sky":"73"},{"hour":"4","civil":"4:00 AM","sky":"73"},{"hour":"5","civil":"5:00 AM","sky":"73"},{"hour":"6","civil":"6:00 AM","sky":"73"},{"hour":"7","civil":"7:00 AM","sky":"73"},{"hour":"8","civil":"8:00 AM","sky":"73"},{"hour":"9","civil":"9:00 AM","sky":"73"},{"hour":"10","civil":"10:00 AM","sky":"73"},{"hour":"11","civil":"11:00 AM","sky":"0"},{"hour":"12","civil":"12:00 PM","sky":"0"},{"hour":"13","civil":"1:00 PM","sky":"0"},{"hour":"14","civil":"2:00 PM","sky":"0"},{"hour":"15","civil":"3:00 PM","sky":"0"},{"hour":"16","civil":"4:00 PM","sky":"0"},{"hour":"17","civil":"5:00 PM","sky":"2"},{"hour":"18","civil":"6:00 PM","sky":"2"},{"hour":"19","civil":"7:00 PM","sky":"2"},{"hour":"20","civil":"8:00 PM","sky":"2"},{"hour":"21","civil":"9:00 PM","sky":"2"},{"hour":"22","civil":"10:00 PM","sky":"2"},{"hour":"23","civil":"11:00 PM","sky":"79"}]},{"zip_code":"94706","forecast":[{"hour":"12","civil":"12:00 PM","sky":"74"},{"hour":"13","civil":"1:00 PM","sky":"74"},{"hour":"14","civil":"2:00 PM","sky":"74"},{"hour":"15","civil":"3:00 PM","sky":"74"},{"hour":"16","civil":"4:00 PM","sky":"74"},{"hour":"17","civil":"5:00 PM","sky":"26"},{"hour":"18","civil":"6:00 PM","sky":"26"},{"hour":"19","civil":"7:00 PM","sky":"26"},{"hour":"20","civil":"8:00 PM","sky":"26"},{"hour":"21","civil":"9:00 PM","sky":"26"},{"hour":"22","civil":"10:00 PM","sky":"26"},{"hour":"23","civil":"11:00 PM","sky":"71"},{"hour":"0","civil":"12:00 AM","sky":"71"},{"hour":"1","civil":"1:00 AM","sky":"71"},{"hour":"2","civil":"2:00 AM","sky":"71"},{"hour":"3","civil":"3:00 AM","sky":"71"},{"hour":"4","civil":"4:00 AM","sky":"71"},{"hour":"5","civil":"5:00 AM","sky":"71"},{"hour":"6","civil":"6:00 AM","sky":"71"},{"hour":"7","civil":"7:00 AM","sky":"71"},{"hour":"8","civil":"8:00 AM","sky":"71"},{"hour":"9","civil":"9:00 AM","sky":"71"},{"hour":"10","civil":"10:00 AM","sky":"71"},{"hour":"11","civil":"11:00 AM","sky":"0"},{"hour":"12","civil":"12:00 PM","sky":"0"},{"hour":"13","civil":"1:00 PM","sky":"0"},{"hour":"14","civil":"2:00 PM","sky":"0"},{"hour":"15","civil":"3:00 PM","sky":"0"},{"hour":"16","civil":"4:00 PM","sky":"0"},{"hour":"17","civil":"5:00 PM","sky":"2"},{"hour":"18","civil":"6:00 PM","sky":"2"},{"hour":"19","civil":"7:00 PM","sky":"2"},{"hour":"20","civil":"8:00 PM","sky":"2"},{"hour":"21","civil":"9:00 PM","sky":"2"},{"hour":"22","civil":"10:00 PM","sky":"2"},{"hour":"23","civil":"11:00 PM","sky":"68"}]},{"zip_code":"94118","forecast":[{"hour":"12","civil":"12:00 PM","sky":"66"},{"hour":"13","civil":"1:00 PM","sky":"66"},{"hour":"14","civil":"2:00 PM","sky":"66"},{"hour":"15","civil":"3:00 PM","sky":"66"},{"hour":"16","civil":"4:00 PM","sky":"66"},{"hour":"17","civil":"5:00 PM","sky":"32"},{"hour":"18","civil":"6:00 PM","sky":"32"},{"hour":"19","civil":"7:00 PM","sky":"32"},{"hour":"20","civil":"8:00 PM","sky":"32"},{"hour":"21","civil":"9:00 PM","sky":"32"},{"hour":"22","civil":"10:00 PM","sky":"32"},{"hour":"23","civil":"11:00 PM","sky":"75"},{"hour":"0","civil":"12:00 AM","sky":"75"},{"hour":"1","civil":"1:00 AM","sky":"75"},{"hour":"2","civil":"2:00 AM","sky":"75"},{"hour":"3","civil":"3:00 AM","sky":"75"},{"hour":"4","civil":"4:00 AM","sky":"75"},{"hour":"5","civil":"5:00 AM","sky":"76"},{"hour":"6","civil":"6:00 AM","sky":"76"},{"hour":"7","civil":"7:00 AM","sky":"76"},{"hour":"8","civil":"8:00 AM","sky":"76"},{"hour":"9","civil":"9:00 AM","sky":"76"},{"hour":"10","civil":"10:00 AM","sky":"76"},{"hour":"11","civil":"11:00 AM","sky":"0"},{"hour":"12","civil":"12:00 PM","sky":"0"},{"hour":"13","civil":"1:00 PM","sky":"0"},{"hour":"14","civil":"2:00 PM","sky":"0"},{"hour":"15","civil":"3:00 PM","sky":"0"},{"hour":"16","civil":"4:00 PM","sky":"0"},{"hour":"17","civil":"5:00 PM","sky":"23"},{"hour":"18","civil":"6:00 PM","sky":"23"},{"hour":"19","civil":"7:00 PM","sky":"23"},{"hour":"20","civil":"8:00 PM","sky":"23"},{"hour":"21","civil":"9:00 PM","sky":"23"},{"hour":"22","civil":"10:00 PM","sky":"23"},{"hour":"23","civil":"11:00 PM","sky":"87"}]},{"zip_code":"94609","forecast":[{"hour":"12","civil":"12:00 PM","sky":"75"},{"hour":"13","civil":"1:00 PM","sky":"75"},{"hour":"14","civil":"2:00 PM","sky":"75"},{"hour":"15","civil":"3:00 PM","sky":"75"},{"hour":"16","civil":"4:00 PM","sky":"75"},{"hour":"17","civil":"5:00 PM","sky":"27"},{"hour":"18","civil":"6:00 PM","sky":"27"},{"hour":"19","civil":"7:00 PM","sky":"27"},{"hour":"20","civil":"8:00 PM","sky":"27"},{"hour":"21","civil":"9:00 PM","sky":"27"},{"hour":"22","civil":"10:00 PM","sky":"27"},{"hour":"23","civil":"11:00 PM","sky":"80"},{"hour":"0","civil":"12:00 AM","sky":"80"},{"hour":"1","civil":"1:00 AM","sky":"80"},{"hour":"2","civil":"2:00 AM","sky":"80"},{"hour":"3","civil":"3:00 AM","sky":"80"},{"hour":"4","civil":"4:00 AM","sky":"80"},{"hour":"5","civil":"5:00 AM","sky":"76"},{"hour":"6","civil":"6:00 AM","sky":"76"},{"hour":"7","civil":"7:00 AM","sky":"76"},{"hour":"8","civil":"8:00 AM","sky":"76"},{"hour":"9","civil":"9:00 AM","sky":"76"},{"hour":"10","civil":"10:00 AM","sky":"76"},{"hour":"11","civil":"11:00 AM","sky":"0"},{"hour":"12","civil":"12:00 PM","sky":"0"},{"hour":"13","civil":"1:00 PM","sky":"0"},{"hour":"14","civil":"2:00 PM","sky":"0"},{"hour":"15","civil":"3:00 PM","sky":"0"},{"hour":"16","civil":"4:00 PM","sky":"0"},{"hour":"17","civil":"5:00 PM","sky":"2"},{"hour":"18","civil":"6:00 PM","sky":"2"},{"hour":"19","civil":"7:00 PM","sky":"2"},{"hour":"20","civil":"8:00 PM","sky":"2"},{"hour":"21","civil":"9:00 PM","sky":"2"},{"hour":"22","civil":"10:00 PM","sky":"2"},{"hour":"23","civil":"11:00 PM","sky":"89"}]},{"zip_code":"94702","forecast":[{"hour":"12","civil":"12:00 PM","sky":"75"},{"hour":"13","civil":"1:00 PM","sky":"75"},{"hour":"14","civil":"2:00 PM","sky":"75"},{"hour":"15","civil":"3:00 PM","sky":"75"},{"hour":"16","civil":"4:00 PM","sky":"75"},{"hour":"17","civil":"5:00 PM","sky":"27"},{"hour":"18","civil":"6:00 PM","sky":"27"},{"hour":"19","civil":"7:00 PM","sky":"27"},{"hour":"20","civil":"8:00 PM","sky":"27"},{"hour":"21","civil":"9:00 PM","sky":"27"},{"hour":"22","civil":"10:00 PM","sky":"27"},{"hour":"23","civil":"11:00 PM","sky":"80"},{"hour":"0","civil":"12:00 AM","sky":"80"},{"hour":"1","civil":"1:00 AM","sky":"80"},{"hour":"2","civil":"2:00 AM","sky":"80"},{"hour":"3","civil":"3:00 AM","sky":"80"},{"hour":"4","civil":"4:00 AM","sky":"80"},{"hour":"5","civil":"5:00 AM","sky":"76"},{"hour":"6","civil":"6:00 AM","sky":"76"},{"hour":"7","civil":"7:00 AM","sky":"76"},{"hour":"8","civil":"8:00 AM","sky":"76"},{"hour":"9","civil":"9:00 AM","sky":"76"},{"hour":"10","civil":"10:00 AM","sky":"76"},{"hour":"11","civil":"11:00 AM","sky":"0"},{"hour":"12","civil":"12:00 PM","sky":"0"},{"hour":"13","civil":"1:00 PM","sky":"0"},{"hour":"14","civil":"2:00 PM","sky":"0"},{"hour":"15","civil":"3:00 PM","sky":"0"},{"hour":"16","civil":"4:00 PM","sky":"0"},{"hour":"17","civil":"5:00 PM","sky":"2"},{"hour":"18","civil":"6:00 PM","sky":"2"},{"hour":"19","civil":"7:00 PM","sky":"2"},{"hour":"20","civil":"8:00 PM","sky":"2"},{"hour":"21","civil":"9:00 PM","sky":"2"},{"hour":"22","civil":"10:00 PM","sky":"2"},{"hour":"23","civil":"11:00 PM","sky":"89"}]},{"zip_code":"94132","forecast":[{"hour":"12","civil":"12:00 PM","sky":"75"},{"hour":"13","civil":"1:00 PM","sky":"75"},{"hour":"14","civil":"2:00 PM","sky":"75"},{"hour":"15","civil":"3:00 PM","sky":"75"},{"hour":"16","civil":"4:00 PM","sky":"75"},{"hour":"17","civil":"5:00 PM","sky":"53"},{"hour":"18","civil":"6:00 PM","sky":"53"},{"hour":"19","civil":"7:00 PM","sky":"53"},{"hour":"20","civil":"8:00 PM","sky":"53"},{"hour":"21","civil":"9:00 PM","sky":"53"},{"hour":"22","civil":"10:00 PM","sky":"53"},{"hour":"23","civil":"11:00 PM","sky":"81"},{"hour":"0","civil":"12:00 AM","sky":"81"},{"hour":"1","civil":"1:00 AM","sky":"81"},{"hour":"2","civil":"2:00 AM","sky":"81"},{"hour":"3","civil":"3:00 AM","sky":"81"},{"hour":"4","civil":"4:00 AM","sky":"81"},{"hour":"5","civil":"5:00 AM","sky":"79"},{"hour":"6","civil":"6:00 AM","sky":"79"},{"hour":"7","civil":"7:00 AM","sky":"79"},{"hour":"8","civil":"8:00 AM","sky":"79"},{"hour":"9","civil":"9:00 AM","sky":"79"},{"hour":"10","civil":"10:00 AM","sky":"79"},{"hour":"11","civil":"11:00 AM","sky":"1"},{"hour":"12","civil":"12:00 PM","sky":"1"},{"hour":"13","civil":"1:00 PM","sky":"1"},{"hour":"14","civil":"2:00 PM","sky":"1"},{"hour":"15","civil":"3:00 PM","sky":"1"},{"hour":"16","civil":"4:00 PM","sky":"1"},{"hour":"17","civil":"5:00 PM","sky":"44"},{"hour":"18","civil":"6:00 PM","sky":"44"},{"hour":"19","civil":"7:00 PM","sky":"44"},{"hour":"20","civil":"8:00 PM","sky":"44"},{"hour":"21","civil":"9:00 PM","sky":"44"},{"hour":"22","civil":"10:00 PM","sky":"44"},{"hour":"23","civil":"11:00 PM","sky":"91"}]},{"zip_code":"94103","forecast":[{"hour":"12","civil":"12:00 PM","sky":"76"},{"hour":"13","civil":"1:00 PM","sky":"76"},{"hour":"14","civil":"2:00 PM","sky":"76"},{"hour":"15","civil":"3:00 PM","sky":"76"},{"hour":"16","civil":"4:00 PM","sky":"76"},{"hour":"17","civil":"5:00 PM","sky":"31"},{"hour":"18","civil":"6:00 PM","sky":"31"},{"hour":"19","civil":"7:00 PM","sky":"31"},{"hour":"20","civil":"8:00 PM","sky":"31"},{"hour":"21","civil":"9:00 PM","sky":"31"},{"hour":"22","civil":"10:00 PM","sky":"31"},{"hour":"23","civil":"11:00 PM","sky":"75"},{"hour":"0","civil":"12:00 AM","sky":"75"},{"hour":"1","civil":"1:00 AM","sky":"75"},{"hour":"2","civil":"2:00 AM","sky":"75"},{"hour":"3","civil":"3:00 AM","sky":"75"},{"hour":"4","civil":"4:00 AM","sky":"75"},{"hour":"5","civil":"5:00 AM","sky":"77"},{"hour":"6","civil":"6:00 AM","sky":"77"},{"hour":"7","civil":"7:00 AM","sky":"77"},{"hour":"8","civil":"8:00 AM","sky":"77"},{"hour":"9","civil":"9:00 AM","sky":"77"},{"hour":"10","civil":"10:00 AM","sky":"77"},{"hour":"11","civil":"11:00 AM","sky":"0"},{"hour":"12","civil":"12:00 PM","sky":"0"},{"hour":"13","civil":"1:00 PM","sky":"0"},{"hour":"14","civil":"2:00 PM","sky":"0"},{"hour":"15","civil":"3:00 PM","sky":"0"},{"hour":"16","civil":"4:00 PM","sky":"0"},{"hour":"17","civil":"5:00 PM","sky":"21"},{"hour":"18","civil":"6:00 PM","sky":"21"},{"hour":"19","civil":"7:00 PM","sky":"21"},{"hour":"20","civil":"8:00 PM","sky":"21"},{"hour":"21","civil":"9:00 PM","sky":"21"},{"hour":"22","civil":"10:00 PM","sky":"21"},{"hour":"23","civil":"11:00 PM","sky":"91"}]},{"zip_code":"94122","forecast":[{"hour":"12","civil":"12:00 PM","sky":"74"},{"hour":"13","civil":"1:00 PM","sky":"74"},{"hour":"14","civil":"2:00 PM","sky":"74"},{"hour":"15","civil":"3:00 PM","sky":"74"},{"hour":"16","civil":"4:00 PM","sky":"74"},{"hour":"17","civil":"5:00 PM","sky":"40"},{"hour":"18","civil":"6:00 PM","sky":"40"},{"hour":"19","civil":"7:00 PM","sky":"40"},{"hour":"20","civil":"8:00 PM","sky":"40"},{"hour":"21","civil":"9:00 PM","sky":"40"},{"hour":"22","civil":"10:00 PM","sky":"40"},{"hour":"23","civil":"11:00 PM","sky":"78"},{"hour":"0","civil":"12:00 AM","sky":"78"},{"hour":"1","civil":"1:00 AM","sky":"78"},{"hour":"2","civil":"2:00 AM","sky":"78"},{"hour":"3","civil":"3:00 AM","sky":"78"},{"hour":"4","civil":"4:00 AM","sky":"78"},{"hour":"5","civil":"5:00 AM","sky":"81"},{"hour":"6","civil":"6:00 AM","sky":"81"},{"hour":"7","civil":"7:00 AM","sky":"81"},{"hour":"8","civil":"8:00 AM","sky":"81"},{"hour":"9","civil":"9:00 AM","sky":"81"},{"hour":"10","civil":"10:00 AM","sky":"81"},{"hour":"11","civil":"11:00 AM","sky":"0"},{"hour":"12","civil":"12:00 PM","sky":"0"},{"hour":"13","civil":"1:00 PM","sky":"0"},{"hour":"14","civil":"2:00 PM","sky":"0"},{"hour":"15","civil":"3:00 PM","sky":"0"},{"hour":"16","civil":"4:00 PM","sky":"0"},{"hour":"17","civil":"5:00 PM","sky":"34"},{"hour":"18","civil":"6:00 PM","sky":"34"},{"hour":"19","civil":"7:00 PM","sky":"34"},{"hour":"20","civil":"8:00 PM","sky":"34"},{"hour":"21","civil":"9:00 PM","sky":"34"},{"hour":"22","civil":"10:00 PM","sky":"34"},{"hour":"23","civil":"11:00 PM","sky":"91"}]},{"zip_code":"94128","forecast":[{"hour":"12","civil":"12:00 PM","sky":"90"},{"hour":"13","civil":"1:00 PM","sky":"90"},{"hour":"14","civil":"2:00 PM","sky":"100"},{"hour":"15","civil":"3:00 PM","sky":"100"},{"hour":"16","civil":"4:00 PM","sky":"100"},{"hour":"17","civil":"5:00 PM","sky":"55"},{"hour":"18","civil":"6:00 PM","sky":"55"},{"hour":"19","civil":"7:00 PM","sky":"55"},{"hour":"20","civil":"8:00 PM","sky":"61"},{"hour":"21","civil":"9:00 PM","sky":"61"},{"hour":"22","civil":"10:00 PM","sky":"61"},{"hour":"23","civil":"11:00 PM","sky":"2"},{"hour":"0","civil":"12:00 AM","sky":"2"},{"hour":"1","civil":"1:00 AM","sky":"2"},{"hour":"2","civil":"2:00 AM","sky":"45"},{"hour":"3","civil":"3:00 AM","sky":"45"},{"hour":"4","civil":"4:00 AM","sky":"45"},{"hour":"5","civil":"5:00 AM","sky":"80"},{"hour":"6","civil":"6:00 AM","sky":"80"},{"hour":"7","civil":"7:00 AM","sky":"80"},{"hour":"8","civil":"8:00 AM","sky":"80"},{"hour":"9","civil":"9:00 AM","sky":"80"},{"hour":"10","civil":"10:00 AM","sky":"80"},{"hour":"11","civil":"11:00 AM","sky":"80"},{"hour":"12","civil":"12:00 PM","sky":"80"},{"hour":"13","civil":"1:00 PM","sky":"80"},{"hour":"14","civil":"2:00 PM","sky":"45"},{"hour":"15","civil":"3:00 PM","sky":"45"},{"hour":"16","civil":"4:00 PM","sky":"45"},{"hour":"17","civil":"5:00 PM","sky":"2"},{"hour":"18","civil":"6:00 PM","sky":"2"},{"hour":"19","civil":"7:00 PM","sky":"2"},{"hour":"20","civil":"8:00 PM","sky":"35"},{"hour":"21","civil":"9:00 PM","sky":"35"},{"hour":"22","civil":"10:00 PM","sky":"35"},{"hour":"23","civil":"11:00 PM","sky":"74"}]},{"zip_code":"94613","forecast":[{"hour":"12","civil":"12:00 PM","sky":"74"},{"hour":"13","civil":"1:00 PM","sky":"74"},{"hour":"14","civil":"2:00 PM","sky":"74"},{"hour":"15","civil":"3:00 PM","sky":"74"},{"hour":"16","civil":"4:00 PM","sky":"74"},{"hour":"17","civil":"5:00 PM","sky":"28"},{"hour":"18","civil":"6:00 PM","sky":"28"},{"hour":"19","civil":"7:00 PM","sky":"28"},{"hour":"20","civil":"8:00 PM","sky":"28"},{"hour":"21","civil":"9:00 PM","sky":"28"},{"hour":"22","civil":"10:00 PM","sky":"28"},{"hour":"23","civil":"11:00 PM","sky":"92"},{"hour":"0","civil":"12:00 AM","sky":"92"},{"hour":"1","civil":"1:00 AM","sky":"92"},{"hour":"2","civil":"2:00 AM","sky":"92"},{"hour":"3","civil":"3:00 AM","sky":"92"},{"hour":"4","civil":"4:00 AM","sky":"92"},{"hour":"5","civil":"5:00 AM","sky":"80"},{"hour":"6","civil":"6:00 AM","sky":"80"},{"hour":"7","civil":"7:00 AM","sky":"80"},{"hour":"8","civil":"8:00 AM","sky":"80"},{"hour":"9","civil":"9:00 AM","sky":"80"},{"hour":"10","civil":"10:00 AM","sky":"80"},{"hour":"11","civil":"11:00 AM","sky":"0"},{"hour":"12","civil":"12:00 PM","sky":"0"},{"hour":"13","civil":"1:00 PM","sky":"0"},{"hour":"14","civil":"2:00 PM","sky":"0"},{"hour":"15","civil":"3:00 PM","sky":"0"},{"hour":"16","civil":"4:00 PM","sky":"0"},{"hour":"17","civil":"5:00 PM","sky":"4"},{"hour":"18","civil":"6:00 PM","sky":"4"},{"hour":"19","civil":"7:00 PM","sky":"4"},{"hour":"20","civil":"8:00 PM","sky":"4"},{"hour":"21","civil":"9:00 PM","sky":"4"},{"hour":"22","civil":"10:00 PM","sky":"4"},{"hour":"23","civil":"11:00 PM","sky":"90"}]},{"zip_code":"94109","forecast":[{"hour":"13","civil":"1:00 PM","sky":"71"},{"hour":"14","civil":"2:00 PM","sky":"71"},{"hour":"15","civil":"3:00 PM","sky":"71"},{"hour":"16","civil":"4:00 PM","sky":"71"},{"hour":"17","civil":"5:00 PM","sky":"27"},{"hour":"18","civil":"6:00 PM","sky":"27"},{"hour":"19","civil":"7:00 PM","sky":"27"},{"hour":"20","civil":"8:00 PM","sky":"27"},{"hour":"21","civil":"9:00 PM","sky":"27"},{"hour":"22","civil":"10:00 PM","sky":"27"},{"hour":"23","civil":"11:00 PM","sky":"73"},{"hour":"0","civil":"12:00 AM","sky":"73"},{"hour":"1","civil":"1:00 AM","sky":"73"},{"hour":"2","civil":"2:00 AM","sky":"73"},{"hour":"3","civil":"3:00 AM","sky":"73"},{"hour":"4","civil":"4:00 AM","sky":"73"},{"hour":"5","civil":"5:00 AM","sky":"74"},{"hour":"6","civil":"6:00 AM","sky":"74"},{"hour":"7","civil":"7:00 AM","sky":"74"},{"hour":"8","civil":"8:00 AM","sky":"74"},{"hour":"9","civil":"9:00 AM","sky":"74"},{"hour":"10","civil":"10:00 AM","sky":"74"},{"hour":"11","civil":"11:00 AM","sky":"0"},{"hour":"12","civil":"12:00 PM","sky":"0"},{"hour":"13","civil":"1:00 PM","sky":"0"},{"hour":"14","civil":"2:00 PM","sky":"0"},{"hour":"15","civil":"3:00 PM","sky":"0"},{"hour":"16","civil":"4:00 PM","sky":"0"},{"hour":"17","civil":"5:00 PM","sky":"11"},{"hour":"18","civil":"6:00 PM","sky":"11"},{"hour":"19","civil":"7:00 PM","sky":"11"},{"hour":"20","civil":"8:00 PM","sky":"11"},{"hour":"21","civil":"9:00 PM","sky":"11"},{"hour":"22","civil":"10:00 PM","sky":"11"},{"hour":"23","civil":"11:00 PM","sky":"87"},{"hour":"0","civil":"12:00 AM","sky":"87"}]},{"zip_code":"94608","forecast":[{"hour":"13","civil":"1:00 PM","sky":"75"},{"hour":"14","civil":"2:00 PM","sky":"75"},{"hour":"15","civil":"3:00 PM","sky":"75"},{"hour":"16","civil":"4:00 PM","sky":"75"},{"hour":"17","civil":"5:00 PM","sky":"27"},{"hour":"18","civil":"6:00 PM","sky":"27"},{"hour":"19","civil":"7:00 PM","sky":"27"},{"hour":"20","civil":"8:00 PM","sky":"27"},{"hour":"21","civil":"9:00 PM","sky":"27"},{"hour":"22","civil":"10:00 PM","sky":"27"},{"hour":"23","civil":"11:00 PM","sky":"80"},{"hour":"0","civil":"12:00 AM","sky":"80"},{"hour":"1","civil":"1:00 AM","sky":"80"},{"hour":"2","civil":"2:00 AM","sky":"80"},{"hour":"3","civil":"3:00 AM","sky":"80"},{"hour":"4","civil":"4:00 AM","sky":"80"},{"hour":"5","civil":"5:00 AM","sky":"76"},{"hour":"6","civil":"6:00 AM","sky":"76"},{"hour":"7","civil":"7:00 AM","sky":"76"},{"hour":"8","civil":"8:00 AM","sky":"76"},{"hour":"9","civil":"9:00 AM","sky":"76"},{"hour":"10","civil":"10:00 AM","sky":"76"},{"hour":"11","civil":"11:00 AM","sky":"0"},{"hour":"12","civil":"12:00 PM","sky":"0"},{"hour":"13","civil":"1:00 PM","sky":"0"},{"hour":"14","civil":"2:00 PM","sky":"0"},{"hour":"15","civil":"3:00 PM","sky":"0"},{"hour":"16","civil":"4:00 PM","sky":"0"},{"hour":"17","civil":"5:00 PM","sky":"2"},{"hour":"18","civil":"6:00 PM","sky":"2"},{"hour":"19","civil":"7:00 PM","sky":"2"},{"hour":"20","civil":"8:00 PM","sky":"2"},{"hour":"21","civil":"9:00 PM","sky":"2"},{"hour":"22","civil":"10:00 PM","sky":"2"},{"hour":"23","civil":"11:00 PM","sky":"89"},{"hour":"0","civil":"12:00 AM","sky":"89"}]},{"zip_code":"94117","forecast":[{"hour":"13","civil":"1:00 PM","sky":"75"},{"hour":"14","civil":"2:00 PM","sky":"75"},{"hour":"15","civil":"3:00 PM","sky":"75"},{"hour":"16","civil":"4:00 PM","sky":"75"},{"hour":"17","civil":"5:00 PM","sky":"31"},{"hour":"18","civil":"6:00 PM","sky":"31"},{"hour":"19","civil":"7:00 PM","sky":"31"},{"hour":"20","civil":"8:00 PM","sky":"31"},{"hour":"21","civil":"9:00 PM","sky":"31"},{"hour":"22","civil":"10:00 PM","sky":"31"},{"hour":"23","civil":"11:00 PM","sky":"76"},{"hour":"0","civil":"12:00 AM","sky":"76"},{"hour":"1","civil":"1:00 AM","sky":"76"},{"hour":"2","civil":"2:00 AM","sky":"76"},{"hour":"3","civil":"3:00 AM","sky":"76"},{"hour":"4","civil":"4:00 AM","sky":"76"},{"hour":"5","civil":"5:00 AM","sky":"78"},{"hour":"6","civil":"6:00 AM","sky":"78"},{"hour":"7","civil":"7:00 AM","sky":"78"},{"hour":"8","civil":"8:00 AM","sky":"78"},{"hour":"9","civil":"9:00 AM","sky":"78"},{"hour":"10","civil":"10:00 AM","sky":"78"},{"hour":"11","civil":"11:00 AM","sky":"0"},{"hour":"12","civil":"12:00 PM","sky":"0"},{"hour":"13","civil":"1:00 PM","sky":"0"},{"hour":"14","civil":"2:00 PM","sky":"0"},{"hour":"15","civil":"3:00 PM","sky":"0"},{"hour":"16","civil":"4:00 PM","sky":"0"},{"hour":"17","civil":"5:00 PM","sky":"29"},{"hour":"18","civil":"6:00 PM","sky":"29"},{"hour":"19","civil":"7:00 PM","sky":"29"},{"hour":"20","civil":"8:00 PM","sky":"29"},{"hour":"21","civil":"9:00 PM","sky":"29"},{"hour":"22","civil":"10:00 PM","sky":"29"},{"hour":"23","civil":"11:00 PM","sky":"91"},{"hour":"0","civil":"12:00 AM","sky":"91"}]},{"zip_code":"94710","forecast":[{"hour":"13","civil":"1:00 PM","sky":"74"},{"hour":"14","civil":"2:00 PM","sky":"74"},{"hour":"15","civil":"3:00 PM","sky":"74"},{"hour":"16","civil":"4:00 PM","sky":"74"},{"hour":"17","civil":"5:00 PM","sky":"26"},{"hour":"18","civil":"6:00 PM","sky":"26"},{"hour":"19","civil":"7:00 PM","sky":"26"},{"hour":"20","civil":"8:00 PM","sky":"26"},{"hour":"21","civil":"9:00 PM","sky":"26"},{"hour":"22","civil":"10:00 PM","sky":"26"},{"hour":"23","civil":"11:00 PM","sky":"71"},{"hour":"0","civil":"12:00 AM","sky":"71"},{"hour":"1","civil":"1:00 AM","sky":"71"},{"hour":"2","civil":"2:00 AM","sky":"71"},{"hour":"3","civil":"3:00 AM","sky":"71"},{"hour":"4","civil":"4:00 AM","sky":"71"},{"hour":"5","civil":"5:00 AM","sky":"71"},{"hour":"6","civil":"6:00 AM","sky":"71"},{"hour":"7","civil":"7:00 AM","sky":"71"},{"hour":"8","civil":"8:00 AM","sky":"71"},{"hour":"9","civil":"9:00 AM","sky":"71"},{"hour":"10","civil":"10:00 AM","sky":"71"},{"hour":"11","civil":"11:00 AM","sky":"0"},{"hour":"12","civil":"12:00 PM","sky":"0"},{"hour":"13","civil":"1:00 PM","sky":"0"},{"hour":"14","civil":"2:00 PM","sky":"0"},{"hour":"15","civil":"3:00 PM","sky":"0"},{"hour":"16","civil":"4:00 PM","sky":"0"},{"hour":"17","civil":"5:00 PM","sky":"2"},{"hour":"18","civil":"6:00 PM","sky":"2"},{"hour":"19","civil":"7:00 PM","sky":"2"},{"hour":"20","civil":"8:00 PM","sky":"2"},{"hour":"21","civil":"9:00 PM","sky":"2"},{"hour":"22","civil":"10:00 PM","sky":"2"},{"hour":"23","civil":"11:00 PM","sky":"68"},{"hour":"0","civil":"12:00 AM","sky":"68"}]},{"zip_code":"94720","forecast":[{"hour":"13","civil":"1:00 PM","sky":"74"},{"hour":"14","civil":"2:00 PM","sky":"74"},{"hour":"15","civil":"3:00 PM","sky":"74"},{"hour":"16","civil":"4:00 PM","sky":"74"},{"hour":"17","civil":"5:00 PM","sky":"25"},{"hour":"18","civil":"6:00 PM","sky":"25"},{"hour":"19","civil":"7:00 PM","sky":"25"},{"hour":"20","civil":"8:00 PM","sky":"25"},{"hour":"21","civil":"9:00 PM","sky":"25"},{"hour":"22","civil":"10:00 PM","sky":"25"},{"hour":"23","civil":"11:00 PM","sky":"48"},{"hour":"0","civil":"12:00 AM","sky":"48"},{"hour":"1","civil":"1:00 AM","sky":"48"},{"hour":"2","civil":"2:00 AM","sky":"48"},{"hour":"3","civil":"3:00 AM","sky":"48"},{"hour":"4","civil":"4:00 AM","sky":"48"},{"hour":"5","civil":"5:00 AM","sky":"53"},{"hour":"6","civil":"6:00 AM","sky":"53"},{"hour":"7","civil":"7:00 AM","sky":"53"},{"hour":"8","civil":"8:00 AM","sky":"53"},{"hour":"9","civil":"9:00 AM","sky":"53"},{"hour":"10","civil":"10:00 AM","sky":"53"},{"hour":"11","civil":"11:00 AM","sky":"0"},{"hour":"12","civil":"12:00 PM","sky":"0"},{"hour":"13","civil":"1:00 PM","sky":"0"},{"hour":"14","civil":"2:00 PM","sky":"0"},{"hour":"15","civil":"3:00 PM","sky":"0"},{"hour":"16","civil":"4:00 PM","sky":"0"},{"hour":"17","civil":"5:00 PM","sky":"1"},{"hour":"18","civil":"6:00 PM","sky":"1"},{"hour":"19","civil":"7:00 PM","sky":"1"},{"hour":"20","civil":"8:00 PM","sky":"1"},{"hour":"21","civil":"9:00 PM","sky":"1"},{"hour":"22","civil":"10:00 PM","sky":"1"},{"hour":"23","civil":"11:00 PM","sky":"32"},{"hour":"0","civil":"12:00 AM","sky":"32"}]},{"zip_code":"94112","forecast":[{"hour":"13","civil":"1:00 PM","sky":"74"},{"hour":"14","civil":"2:00 PM","sky":"74"},{"hour":"15","civil":"3:00 PM","sky":"74"},{"hour":"16","civil":"4:00 PM","sky":"74"},{"hour":"17","civil":"5:00 PM","sky":"34"},{"hour":"18","civil":"6:00 PM","sky":"34"},{"hour":"19","civil":"7:00 PM","sky":"34"},{"hour":"20","civil":"8:00 PM","sky":"34"},{"hour":"21","civil":"9:00 PM","sky":"34"},{"hour":"22","civil":"10:00 PM","sky":"34"},{"hour":"23","civil":"11:00 PM","sky":"76"},{"hour":"0","civil":"12:00 AM","sky":"76"},{"hour":"1","civil":"1:00 AM","sky":"76"},{"hour":"2","civil":"2:00 AM","sky":"76"},{"hour":"3","civil":"3:00 AM","sky":"76"},{"hour":"4","civil":"4:00 AM","sky":"76"},{"hour":"5","civil":"5:00 AM","sky":"77"},{"hour":"6","civil":"6:00 AM","sky":"77"},{"hour":"7","civil":"7:00 AM","sky":"77"},{"hour":"8","civil":"8:00 AM","sky":"77"},{"hour":"9","civil":"9:00 AM","sky":"77"},{"hour":"10","civil":"10:00 AM","sky":"77"},{"hour":"11","civil":"11:00 AM","sky":"0"},{"hour":"12","civil":"12:00 PM","sky":"0"},{"hour":"13","civil":"1:00 PM","sky":"0"},{"hour":"14","civil":"2:00 PM","sky":"0"},{"hour":"15","civil":"3:00 PM","sky":"0"},{"hour":"16","civil":"4:00 PM","sky":"0"},{"hour":"17","civil":"5:00 PM","sky":"30"},{"hour":"18","civil":"6:00 PM","sky":"30"},{"hour":"19","civil":"7:00 PM","sky":"30"},{"hour":"20","civil":"8:00 PM","sky":"30"},{"hour":"21","civil":"9:00 PM","sky":"30"},{"hour":"22","civil":"10:00 PM","sky":"30"},{"hour":"23","civil":"11:00 PM","sky":"91"},{"hour":"0","civil":"12:00 AM","sky":"91"}]},{"zip_code":"94129","forecast":[{"hour":"13","civil":"1:00 PM","sky":"71"},{"hour":"14","civil":"2:00 PM","sky":"71"},{"hour":"15","civil":"3:00 PM","sky":"71"},{"hour":"16","civil":"4:00 PM","sky":"71"},{"hour":"17","civil":"5:00 PM","sky":"29"},{"hour":"18","civil":"6:00 PM","sky":"29"},{"hour":"19","civil":"7:00 PM","sky":"29"},{"hour":"20","civil":"8:00 PM","sky":"29"},{"hour":"21","civil":"9:00 PM","sky":"29"},{"hour":"22","civil":"10:00 PM","sky":"29"},{"hour":"23","civil":"11:00 PM","sky":"74"},{"hour":"0","civil":"12:00 AM","sky":"74"},{"hour":"1","civil":"1:00 AM","sky":"74"},{"hour":"2","civil":"2:00 AM","sky":"74"},{"hour":"3","civil":"3:00 AM","sky":"74"},{"hour":"4","civil":"4:00 AM","sky":"74"},{"hour":"5","civil":"5:00 AM","sky":"75"},{"hour":"6","civil":"6:00 AM","sky":"75"},{"hour":"7","civil":"7:00 AM","sky":"75"},{"hour":"8","civil":"8:00 AM","sky":"75"},{"hour":"9","civil":"9:00 AM","sky":"75"},{"hour":"10","civil":"10:00 AM","sky":"75"},{"hour":"11","civil":"11:00 AM","sky":"0"},{"hour":"12","civil":"12:00 PM","sky":"0"},{"hour":"13","civil":"1:00 PM","sky":"0"},{"hour":"14","civil":"2:00 PM","sky":"0"},{"hour":"15","civil":"3:00 PM","sky":"0"},{"hour":"16","civil":"4:00 PM","sky":"0"},{"hour":"17","civil":"5:00 PM","sky":"22"},{"hour":"18","civil":"6:00 PM","sky":"22"},{"hour":"19","civil":"7:00 PM","sky":"22"},{"hour":"20","civil":"8:00 PM","sky":"22"},{"hour":"21","civil":"9:00 PM","sky":"22"},{"hour":"22","civil":"10:00 PM","sky":"22"},{"hour":"23","civil":"11:00 PM","sky":"88"},{"hour":"0","civil":"12:00 AM","sky":"88"}]},{"zip_code":"94127","forecast":[{"hour":"13","civil":"1:00 PM","sky":"73"},{"hour":"14","civil":"2:00 PM","sky":"73"},{"hour":"15","civil":"3:00 PM","sky":"73"},{"hour":"16","civil":"4:00 PM","sky":"73"},{"hour":"17","civil":"5:00 PM","sky":"41"},{"hour":"18","civil":"6:00 PM","sky":"41"},{"hour":"19","civil":"7:00 PM","sky":"41"},{"hour":"20","civil":"8:00 PM","sky":"41"},{"hour":"21","civil":"9:00 PM","sky":"41"},{"hour":"22","civil":"10:00 PM","sky":"41"},{"hour":"23","civil":"11:00 PM","sky":"78"},{"hour":"0","civil":"12:00 AM","sky":"78"},{"hour":"1","civil":"1:00 AM","sky":"78"},{"hour":"2","civil":"2:00 AM","sky":"78"},{"hour":"3","civil":"3:00 AM","sky":"78"},{"hour":"4","civil":"4:00 AM","sky":"78"},{"hour":"5","civil":"5:00 AM","sky":"80"},{"hour":"6","civil":"6:00 AM","sky":"80"},{"hour":"7","civil":"7:00 AM","sky":"80"},{"hour":"8","civil":"8:00 AM","sky":"80"},{"hour":"9","civil":"9:00 AM","sky":"80"},{"hour":"10","civil":"10:00 AM","sky":"80"},{"hour":"11","civil":"11:00 AM","sky":"0"},{"hour":"12","civil":"12:00 PM","sky":"0"},{"hour":"13","civil":"1:00 PM","sky":"0"},{"hour":"14","civil":"2:00 PM","sky":"0"},{"hour":"15","civil":"3:00 PM","sky":"0"},{"hour":"16","civil":"4:00 PM","sky":"0"},{"hour":"17","civil":"5:00 PM","sky":"34"},{"hour":"18","civil":"6:00 PM","sky":"34"},{"hour":"19","civil":"7:00 PM","sky":"34"},{"hour":"20","civil":"8:00 PM","sky":"34"},{"hour":"21","civil":"9:00 PM","sky":"34"},{"hour":"22","civil":"10:00 PM","sky":"34"},{"hour":"23","civil":"11:00 PM","sky":"91"},{"hour":"0","civil":"12:00 AM","sky":"91"}]}]